Workbook

Sheet Consolidado_OUC-FL
F2: OPERAÇÃO URBANA CONSORCIADA FARIA LIMA
F3: Lei 13.769/04, alterada pelas leis 13.871/04, 15.519/11, 16.242/15 e 18.175/24
F4: POSIÇÃO EM 08/04/2026
F6: QUADRO GERAL DE DISTRIBUIÇÃO DE ESTOQUES DE ACA EM M² - LEI 13.769/2004
F7: SETORES | G7: ESTOQUE MÁXIMO (m²) PREVISTO PARA OS SETORES | I7: ESTOQUE MÁXIMO PREVISTO PARA OUCFL - LEI 13.769/04 ( R+ nR) | J7: ESTOQUE CONSUMIDO (m²) - LEI 13.769/04 | L7: SALDO DE ESTOQUE MÁXIMO PREVISTO PARA OS SETORES (Remanescente lei 13.769/04) | N7: ESTOQUE (m²) À RESTITUIR APÓS DESVINCULAÇÃO OU MODIFICAÇÃO DE USO (90 dias) | P7: SALDO DE ESTOQUE GERAL DISPONÍVEL PARA A OPERAÇÃO URBANA
G8: R | H8: NR | J8: R | K8: NR | L8: R | M8: NR | N8: R | O8: NR | P8: R | Q8: NR
F9: HELIO PELEGRINO | G9: 292445 | H9: 182505 | I9: =G9+H9 -> 474950 | J9: =279084.28 -> 279084.28 | K9: =162600.47 -> 162600.47 | L9: =(G9-J9)+N9 -> 13360.72 | M9: =(H9-K9)+O9 -> 19904.53 | N9: 0 | O9: 0 | P9: =N14 -> 22996.43 | X9: 13360.72 | Y9: 19904.53
F10: FARIA LIMA | G10: 288190 | H10: 73715 | I10: =G10+H10 -> 361905 | J10: =133370.09 -> 133370.09 | K10: =73552.78 -> 73552.78 | L10: =(G10-J10)+N10 -> 161822.14 | M10: =(H10-K10)+O10 -> 162.22 | N10: =GETPIVOTDATA("Soma de ACA-R",'5_18175'!$A$30,"SETOR OUC","FARIA LIMA") -> 7002.23 | O10: 0 | X10: 168824.37 | Y10: 162.22
F11: PINHEIROS | G11: 286695 | H11: 96600 | I11: =G11+H11 -> 383295 | J11: =146445.55 -> 146445.55 | K11: =95217.97 -> 95217.97 | L11: =(G11-J11)+N11 -> 140249.45 | M11: =(H11-K11)+O11 -> 1382.03 | N11: 0 | O11: 0 | X11: 140249.45 | Y11: 1382.03
F12: OLIMPÍADAS | G12: 190440 | H12: 95565 | I12: =G12+H12 -> 286005 | J12: =87199.88 -> 87199.88 | K12: 95563.02 | L12: =(G12-J12)+N12 -> 119234.32 | M12: =(H12-K12)+O12 -> 1.98 | N12: =GETPIVOTDATA("Soma de ACA-R",'5_18175'!$A$30,"SETOR OUC","OLIMPÍADAS") -> 15994.2 | O12: 0 | X12: 103240.12 | Y12: 1.98
F13: Total | G13: =SUM(G9:G12) -> 1057770 | H13: =SUM(H9:H12) -> 448385 | I13: =SUM(I9:I12) -> 1506155 | J13: =SUM(J9:J12) -> 646099.8 | K13: =SUM(K9:K12) -> 426934.24 | L13: =SUM(L9:L12) -> 434666.63 | M13: =SUM(M9:M12) -> 21450.76 | N13: =SUM(N9:N12) -> 22996.43 | O13: =SUM(O9:O12) -> 0
G14: =G13+H13 -> 1506155 | J14: =J13+K13 -> 1073034 | L14: =L13+M13 -> 456117.39 | N14: =N13+O13 -> 22996.43
F16: QUADRO GERAL DE DISTRIBUIÇÃO DE ESTOQUES DE ACA EM M² - (A PARTIR DA LEI 18.175/24)
F17: SETORES | G17: ESTOQUE MÁXIMO (por uso e por setor(m²) PREVISTO PARA OS SETORES ( LEI 13.769/04) | I17: ESTOQUE MÁXIMO PREVISTO POR SETOR PARA OUCFL - Lei 18.175/24 | J17: ESTOQUE CONSUMIDO (m²) - (Lei 13.769/04) | L17: ESTOQUE EM CONSUMIDO (m²) - (a partir da Lei 18.175/24) | N17: ESTOQUE EM ANALISE (m²) - (a partir da Lei 18.175/24) | P17: ESTOQUE MAXIMO (m²) PREVISTO PARA OS SETORES PELA LEI 18.175/24 | R17: SALDO DE ESTOQUE GERAL DISPONIVEL PARA A OPERAÇÃO URBANA - lei 18.175/24
G18: R | H18: NR | J18: R | K18: NR | L18: R | M18: NR | N18: R | O18: NR | P18: R | Q18: NR | R18: R | S18: NR
F19: HELIO PELEGRINO | G19: 292445 | H19: 182505 | I19: 576700 | J19: =J9 -> 279084.28 | K19: =K9 -> 162600.47 | L19: ='5_18175'!R7 -> 21066.57 | M19: ='5_18175'!S7 -> 12448.27 | N19: =GETPIVOTDATA("Soma de ACA-R",'5_18175'!$A$6,"SETOR OUC","HÉLIO PELEGRINO") -> 4854.71 | O19: =GETPIVOTDATA("Soma de ACA-NR",'5_18175'!$A$6,"SETOR OUC","HÉLIO PELEGRINO") -> 175.83 | P19: =101750-L19-M19 -> 68235.16 | R19: =250000-L24 -> 128601.6
F20: FARIA LIMA | G20: 288190 | H20: 73715 | I20: 402905 | J20: =J10 -> 133370.09 | K20: =K10 -> 73552.78 | L20: ='5_18175'!R8 -> 19231.15 | M20: ='5_18175'!S8 -> 7722.52 | N20: =GETPIVOTDATA("Soma de ACA-R",'5_18175'!$A$6,"SETOR OUC","FARIA LIMA") -> 0 | O20: =GETPIVOTDATA("Soma de ACA-NR",'5_18175'!$A$6,"SETOR OUC","FARIA LIMA") -> 0 | P20: =41000-L20-M20 -> 14046.33
F21: PINHEIROS | G21: 286695 | H21: 96600 | I21: 437145 | J21: =J11 -> 146445.55 | K21: =K11 -> 95217.97 | L21: ='5_18175'!R9 -> 21914.1 | M21: ='5_18175'!S9 -> 0 | N21: =GETPIVOTDATA("Soma de ACA-R",'5_18175'!$A$6,"SETOR OUC","PINHEIROS") -> 0 | O21: =GETPIVOTDATA("Soma de ACA-NR",'5_18175'!$A$6,"SETOR OUC","PINHEIROS") -> 0 | P21: =53850-L21-M21 -> 31935.9
F22: OLIMPÍADAS | G22: 190440 | H22: 95565 | I22: 339405 | J22: =J12 -> 87199.88 | K22: =K12 -> 95563.02 | L22: ='5_18175'!R10 -> 8140.2 | M22: ='5_18175'!S10 -> 30875.59 | N22: =GETPIVOTDATA("Soma de ACA-R",'5_18175'!$A$6,"SETOR OUC","OLIMPÍADAS") -> 0 | O22: =GETPIVOTDATA("Soma de ACA-NR",'5_18175'!$A$6,"SETOR OUC","OLIMPÍADAS") -> 0 | P22: =53400-L22-M22 -> 14384.21
F23: Total | G23: =SUM(G19:G22) -> 1057770 | H23: =SUM(H19:H22) -> 448385 | I23: =SUM(I19:I22) -> 1756155 | J23: =SUM(J19:J22) -> 646099.8 | K23: =SUM(K19:K22) -> 426934.24 | L23: =SUM(L19:L22) -> 70352.02 | M23: =SUM(M19:M22) -> 51046.38 | N23: =SUM(N19:N22) -> 4854.71 | O23: =SUM(O19:O22) -> 175.83 | P23: =SUM(P19:Q22) -> 128601.6 | U23: =R19-N24 -> 123571.06
G24: =G23+H23 -> 1506155 | J24: =J23+K23 -> 1073034 | L24: =L23+M23 -> 121398.4 | N24: =N23+O23 -> 5030.54
F26: LIMITE DE ESTOQUE (m²) PARA EFEITO DE OFERTA DE CEPAC | I26: RESUMO DE CEPAC | L26: SETORES | M26: CEPAC CONVERTIDO | P26: SETORES | Q26: CEPAC DESVINCULADO
F27: Estoque GERAL (aprovado pela 18.175/24) | G27: 2500000 | I27: LEILOADO | J27: 664030 | M27: ACA | N27: USO E PARÂMETROS | Q27: ACA | R27: USO E PARÂMETROS | X27: SALDO DE ESTOQUE MÁXIMO DISPONIVEL POR SETOR (Lei 13.769/04 + lei 18.175/24) | Z27: ESTOQUE (m²) PREVISTO PARA OS SETORES PELA LEI 18.175/24 DESCONTADAS PROPOSTAS APROVADAS | AB27: SALDO DE ESTOQUE GERAL DISPONIVEL PARA A OPERAÇÃO URBANA - lei 18.175/24 + ESTOQUE DEVOLVIDO POR DESVINCULAÇÃO E MUDANÇA DE USO
F28: Estoque consumido Lei 11.732/95 (*) | G28: 940000 | I28: COLOCAÇÃO PRIVADA | J28: 117452 | L28: HÉLIO PELEGRINO | M28: 266344 | N28: 33269 | P28: HÉLIO PELEGRINO | Q28: =348+424+1943+2211 -> 4926 | R28: 0 | X28: Residencial | Y28: Não Residencial | Z28: Residencial | AA28: Não Residencial | AB28: Residencial | AC28: Não Residencial
F29: LIMITE DE ESTOQUE - Lei 18.175/25 | G29: 1560000 | I29: CONVERTIDO | J29: -774382 | L29: FARIA LIMA | M29: 199360 | N29: 13377 | P29: FARIA LIMA | Q29: =1335+6009+2239+38 -> 9621 | R29: =45+1470+558 -> 2073 | X29: =N9 -> 0 | Y29: =O9 -> 0 | Z29: =P19 -> 68235.16 | AB29: =Z34+X35 -> 151598.03
F30: Estoque Consumido Lei 11.732/95 (**) | G30: 244719.95 | I30: EM CIRCULAÇÃO | J30: =SUM(J27:J29) -> 7100 | L30: PINHEIROS | M30: 93446 | N30: 14827 | P30: PINHEIROS | Q30: =2343+72 -> 2415 | R30: 2343 | X30: =N10 -> 7002.23 | Y30: =O10 -> 0 | Z30: =P20 -> 14046.33
F31: Estoque Consumido Lei 13.769/04 (***) | G31: =1065280.05+N10 -> 1072282.3 | I31: CEPAC - Total | J31: 1000000 | L31: OLIMPÍADAS | M31: 147927 | N31: 5832 | P31: OLIMPÍADAS | Q31: 174 | R31: 0 | X31: =N11 -> 0 | Y31: =O11 -> 0 | Z31: =P21 -> 31935.9
F32: Estoque Consumido Lei 18.175/24 | G32: =L24 -> 121398.4 | I32: CEPAC - Saldo | J32: =J31-(J27+J28) -> 218518 | L32: SUB-TOTAL | M32: =SUM(M28:M31) -> 707077 | N32: =SUM(N28:N31) -> 67305 | P32: TOTAL | Q32: =SUM(Q28:Q31) -> 17136 | R32: =SUM(R28:R31) -> 4416 | X32: =N12 -> 15994.2 | Y32: =O12 -> 0 | Z32: =P22 -> 14384.21
F33: Estoque Restituído após desvinculação e/ou alteração de Certidão (Portaria SMDU.G 074/2012 e Decreto 60435/2021) | G33: 0 | L33: TOTAL | M33: =M32+N32 -> 774382
F34: SALDO ESTOQUE GERAL DISPONÍVEL | G34: =G27-G28-G30-G31-G32 -> 121599.37 | P34: Obs: Verificar no site o detalhamento das desvinculações, com as respectivas datas de desvinculação, para observância do estabelecido no Decreto nº 53.094/2012, artigo 37, parágrafos § 4º e § 5º e Portaria nº 74/2012/SMDU.G | X34: =SUM(X29:X32) -> 22996.43 | Y34: =SUM(Y29:Y32) -> 0 | Z34: =SUM(Z29:AA32) -> 128601.6
F35: (*) Estoque consumido na lei 11.732/1998 | X35: =X34+Y34 -> 22996.43
F36: (**) Estoque consumido após a Lei 13.769/04 pago com outorga
F37: (***) Estoque consumido na lei 13.769/04

Sheet 5_18175
A1: STATUS PA | B1: ANALISE | E1: STATUS PA | F1: DEFERIDO
A2: SITUACAO | B2: (Tudo) | E2: SITUACAO | F2: VALIDA
A3: LEI | B3: 18.175/2024 | E3: LEI | F3: 18.175/2024
A4: REQUERIMENTO | B4: (Vários itens) | E4: REQUERIMENTO | F4: (Vários itens)
I5: BENEFICIOS
A6: Rótulos de Linha | B6: Soma de ACA-R | C6: Soma de ACA-NR | E6: Rótulos de Linha | F6: Soma de ACA-R | G6: Soma de ACA-NR | I6: R | K6: NR | Q6: Rótulos de Linha | R6: Soma de ACA-R | S6: Soma de ACA-NR
A7: HÉLIO PELEGRINO | B7: 4854.71 | C7: 175.83 | E7: HÉLIO PELEGRINO | F7: 23064.61 | G7: 13405.25 | I7: 239.24 | J7: 1758.8 | K7: 956.98 | Q7: HÉLIO PELEGRINO | R7: =23064.61-I7-J7 -> 21066.57 | S7: =13405.25-K7 -> 12448.27
A8: FARIA LIMA | E8: FARIA LIMA | F8: 19706.23 | G8: 8310.41 | I8: 475.08 | K8: 587.89 | Q8: FARIA LIMA | R8: =19706.23-I8 -> 19231.15 | S8: =8310.41-K8 -> 7722.52
A9: PINHEIROS | E9: PINHEIROS | F9: 26192.98 | G9: 0 | I9: 1407.54 | J9: 2871.34 | Q9: PINHEIROS | R9: =26192.98-I9-J9 -> 21914.1 | S9: 0
A10: OLIMPÍADAS | E10: OLIMPÍADAS | F10: 8415.63 | G10: 39872.16 | I10: 275.43 | K10: 1101.71 | L10: 1497.96 | M10: 4080 | N10: 1263.4 | O10: 1053.5 | Q10: OLIMPÍADAS | R10: =8415.63-I10 -> 8140.2 | S10: =39872.16-K10-L10-M10-N10-O10 -> 30875.59
A11: Total Geral | B11: 4854.71 | C11: 175.83 | E11: Total Geral | F11: 77379.45 | G11: 61587.82 | Q11: Total Geral | R11: =SUM(R7:R10) -> 70352.02 | S11: =SUM(S7:S10) -> 51046.38
K12: =K7+K8+K10+L10+M10+N10+O10 -> 10541.44
A13: STATUS PA | B13: ANALISE | E13: STATUS PA | F13: DEFERIDO
A14: SITUACAO | B14: (Tudo) | E14: SITUACAO | F14: VALIDA
A15: LEI | B15: 18.175/2024 | E15: LEI | F15: 18.175/2024
A16: REQUERIMENTO | B16: (Vários itens) | E16: REQUERIMENTO | F16: (Vários itens)
A18: Rótulos de Linha | B18: Soma de CEPAC ACA | C18: Soma de CEPAC PARAMETROS | E18: Rótulos de Linha | F18: Soma de CEPAC ACA | G18: Soma de CEPAC PARAMETROS
A19: HÉLIO PELEGRINO | B19: 1906 | C19: 0 | E19: HÉLIO PELEGRINO | F19: 25911 | G19: 0
A20: FARIA LIMA | E20: FARIA LIMA | F20: 17288 | G20: 0
A21: PINHEIROS | E21: PINHEIROS | F21: 9919 | G21: 0
A22: OLIMPÍADAS | E22: OLIMPÍADAS | F22: 33050 | G22: 3190
A23: Total Geral | B23: 1906 | C23: 0 | E23: Total Geral | F23: 86168 | G23: 3190
A25: STATUS PA | B25: (Tudo)
A26: SITUACAO | B26: (Tudo)
A27: LEI | B27: (Tudo)
A28: REQUERIMENTO | B28: DESVINCULACAO
A30: Rótulos de Linha | B30: Soma de ACA-R | C30: Soma de ACA-NR
A31: FARIA LIMA | B31: 7002.23
A32: PINHEIROS
A33: OLIMPÍADAS | B33: 15994.2
A34: (vazio)
A35: Total Geral | B35: 22996.43

Sheet 1_controle_codigo
A1: PROPOSTA | B1: CERTIDAO | C1: STATUS CERTIDAO | D1: ANO CERTIDAO | E1: INTERESSADO | F1: CONTRIBUINTE - SQL | G1: SETOR | H1: PA | I1: STATUS DO PA | J1: TIPO DE CONTRAPARTIDA
A2: XX-0000 | B2: XX-000/0000 | C2: VALIDA OU CANCELADA | D2: 0000 | E2: XXXXXXXXXX | F2: 000.000.0000-0 | G2: XXXXX | H2: 0000.0000/0000000-0 | I2: DEFERIDO, INDEFERIDO OU ANALISE | J2: OODC, CEPAC | K2: MODELO
A3: FL-0001 | B3: FL-005/1995 | D3: 1995 | E3: CAPEL | F3: 083.206.0054-5/ 0055-3/ 0056-1 | G3: FARIA LIMA | H3: 13-000.321-95*05 | I3: DEFERIDO
A4: FL-0002 | B4: FL-012/1995 | D4: 1995 | E4: COMEPAR MALIK | F4: 299.009.0040-3/ 0042-1/ 0043-8/ 0044-6/ 0045-4/ 0052-7/ 0054-3 | G4: FARIA LIMA | H4: 13-000.366-95*35 | I4: DEFERIDO
A5: FL-0003 | B5: FL-025/1996 | D5: 1996 | E5: SAO LOURENCO | F5: 015.080.0222-3/0045-1 | G5: FARIA LIMA | H5: 13-000.578-95*03 | I5: DEFERIDO
A6: FL-0004 | B6: FL-103/1996 | D6: 1996 | E6: JHS | F6: 016.154.0005-2/ 0021-4/ 0022-2/ 0034-6/ 0035-4 | H6: 13-000.586-95*31 | I6: DEFERIDO
A7: FL-0004 | B7: FL-135/1997 | D7: 1997 | E7: SERPLAN | F7: 016.154.0005-2, 016.154.0021-4, 016.154.0035-4, 016.154.0034-6, 016.154.0022-2, 016.154.0024-9, 016.154.0025-7 | H7: 1995-0.017.225-9 | I7: DEFERIDO
A8: FL-0005
A9: FL-0006
A10: FL-0007 | B10: FL-063/1997 | D10: 1997 | E10: VENDOME | F10: 299.014.0097-8/0081-1 | G10: HELIO PELEGRINO | H10: 1995-0.017.263-1 | I10: DEFERIDO
A11: FL-0007 | B11: FL-016/2000 | D11: 2000 | E11: VENDOME | F11: 299.014.0097-8/0081-1 | G11: HELIO PELEGRINO | H11: 1995-0.017.263-1 | I11: DEFERIDO
A12: FL-0008 | B12: FL-112/1997 | D12: 1997 | E12: PETER MURANYI | F12: 015.073.0120-0 | G12: PINHEIROS | H12: 1995-0.017.213-5 | I12: DEFERIDO
A13: FL-0009
A14: FL-0010 | B14: FL-038/1996 | D14: 1996 | E14: SOCIEDADE CIVIL PALMARES | F14: 083.007.0024-2/23-4/39-0/43-9/42-0 | G14: PINHEIROS | H14: 13-000.777-95*30 | I14: DEFERIDO
A15: FL-0011 | B15: FL-102/1996 | D15: 1996 | E15: LUAN | F15: 299.003.0349-9 | H15: 13-000.788-95*56 | I15: DEFERIDO
A16: FL-0011 | B16: FL-071/1997 | D16: 1997 | E16: LUAN | F16: 299.033.0349-9 | H16: 1995-0.017.301-8 | I16: DEFERIDO
A17: FL-0012 | B17: FL-061/1996 | D17: 1996 | E17: KAUFFMANN | F17: 299.022.0152-9/0026-3/0036-0/0029-8/0180-4 /0165-0 | G17: FARIA LIMA | H17: 13-000.795-95*11 | I17: DEFERIDO
A18: FL-0012 | B18: FL-074/1996 | D18: 1996 | E18: KAUFFMANN | F18: 299.022.0152-9/0026-3/0036-0/0029-8/0180-4/0165-0 | G18: FARIA LIMA | H18: 13-000.795-95*11 | I18: DEFERIDO
A19: FL-0013
A20: FL-0014 | B20: FL-020/1996 | D20: 1996 | E20: KLAPART | F20: 083.103.0064 -6/0017-4 | G20: PINHEIROS | H20: 13-000.911-95*10 | I20: DEFERIDO
A21: FL-0015 | B21: FL-065/1996 | D21: 1996 | E21: RACIONAL | F21: 299.019.0035-0, 299019-0032-6, 299.019.0087-3, 299.019.0033-4, 299.019.0034-2 | G21: FARIA LIMA | H21: 13-000.930-95*65 | I21: DEFERIDO
A22: FL-0016 | B22: FL-071/1996 | D22: 1996 | E22: TAQUARI | F22: 015.031.0034-0, 015.031.0035-9, 015.031.0036-7, 015.031.0037-5 | G22: FARIA LIMA | H22: 13-000.878-95*47 | I22: DEFERIDO
A23: FL-0017 | B23: FL-039/1996 | D23: 1996 | E23: MARITIMA | F23: 299.028.0045-7 | H23: 13-000.969-95*09 | I23: DEFERIDO
A24: FL-0018
A25: FL-0019 | B25: FL-010/1996 | D25: 1996 | E25: ACHE | F25: 083.007.0035-8 | G25: PINHEIROS | H25: 13-000.928.95*13 | I25: DEFERIDO
A26: FL-0019 | B26: FL-058/1996 | D26: 1996 | E26: RUY OHTAKE | F26: 083.007.0035-8 | G26: PINHEIROS | H26: 13-000.928.95*13 | I26: DEFERIDO | K26: PERMITIDO GABARITO ACIMA DE 25m (CNLU)
A27: FL-0019 | B27: FL-014/1998 | D27: 1998 | E27: ACHE | F27: 083.007.0005-6, 083.007.0027-7, 083.007.0028-5, 083.007.0035-8 | G27: PINHEIROS | H27: 1995-0.017.346-8 | I27: DEFERIDO
A28: FL-0019 | B28: FL-001/2000 | D28: 2000 | E28: ACHE | F28: 083.007.0005-6, 083.007.0027-7, 083.007.0028-5, 083.007.0035-8 | G28: PINHEIROS | H28: 1995-0.017.346-8 | I28: DEFERIDO
A29: FL-0020 | B29: FL-021/1996 | D29: 1996 | E29: GUSTAVO HALBREICH | F29: 015.074.0049-7/0111-6/0091-8 | G29: PINHEIROS | H29: 13-000.004-96*25 | I29: DEFERIDO
A30: FL-0021 | B30: FL-029/1996 | D30: 1996 | E30: FANY TABACOW | F30: 015.092.0016-9 | G30: PINHEIROS | H30: 13-000.069-96*70 | I30: DEFERIDO
A31: FL-0022 | B31: FL-034/1996 | D31: 1996 | E31: INPAR | F31: 299.073.0019-3/0018-5/0022-3/0020-7 | G31: OLIMPIADAS | H31: 13-000.111-96*35 | I31: DEFERIDO
A32: FL-0023
A33: FL-0024
A34: FL-0025
A35: FL-0026 | B35: FL-040/1997 | D35: 1997 | E35: ANSELMO RODRIGUES | F35: 015.100.0079-8 | G35: FARIA LIMA | H35: 13-000.204-96*41 | I35: DEFERIDO
A36: FL-0027
A37: FL-0028 | B37: FL-043/1997 | D37: 1997 | E37: GASPAR E ASSOCIADOS | F37: 083.110.0021-2 | G37: FARIA LIMA | H37: 13-000.211-96*80 | I37: DEFERIDO
A38: FL-0029 | B38: FL-042/2000 | D38: 2000 | E38: DAVILAR | F38: 299.124.0001- 1/0002-8/0003-6/0004-4/0005-2/0006-0/0007-9 | G38: FARIA LIMA | H38: 1996-0.029.276-0 | I38: DEFERIDO
A39: FL-0030
A40: FL-0031 | B40: FL-024/1997 | D40: 1997 | E40: ZABO | F40: 041.287.0017-7/0018-5/0019-3 e 0020-7 | G40: HELIO PELEGRINO | H40: 13-000.353-96*74 | I40: DEFERIDO
A41: FL-0031 | B41: FL-002/2004 | D41: 2004 | E41: QUEIROZ GALVAO | F41: 041.287.0058-4 (041.287.0017-7, 041.287.0018-5, 041.287.0019-3, 041.287.0020-7) e 041.287.0027-4 | G41: HELIO PELEGRINO | H41: 2003-0.285.966-3 | I41: DEFERIDO
A42: FL-0032 | B42: FL-104/1996 | D42: 1996 | E42: TECNISA | F42: 084.248.0051-6 | G42: FARIA LIMA | H42: 13-000.355-96*08 | I42: DEFERIDO
A43: FL-0033 | B43: FL-033/1997 | D43: 1997 | E43: SCHAHIN CURY | F43: 041.061.0012-6; 041.061.0179-3 | G43: HELIO PELEGRINO | H43: 13-000.182-96*83 | I43: DEFERIDO
A44: FL-0034 | B44: FL-032/1997 | D44: 1997 | E44: SCHAHIN CURY | F44: 041.061.0012-6; 041.061.0179-3 | G44: HELIO PELEGRINO | H44: 13-000.183-96*46 | I44: DEFERIDO
A45: FL-0034 | B45: FL-001/1998 | D45: 1998 | E45: SCHAHIN CURY | F45: 041.061.0012-6; 041.061.0179-3 | G45: HELIO PELEGRINO | H45: 1996-0.029.233-7 | I45: DEFERIDO
A46: FL-0035 | B46: FL-041/1998 | D46: 1998 | E46: SAO LUIZ | F46: 016.162.0166-5, 016.162.0004-9, 016.162.0005-7, 016.162.0007-3, 016.162.0006-5, 016.162.0008-1, 016.162.0009-1 | G46: HELIO PELEGRINO | H46: 1996-0.029.323-6 | I46: DEFERIDO
A47: FL-0036 | B47: FL-058/1997 | D47: 1997 | E47: DAVILAR | F47: 299.003.0050-3, 299.003.0051-1, 299.003.0049-1 ,299.003.0347-2, 299.003.0045-7, 299.003.0053-8, 299.003.0046-5, 299.003.0054-6, 299.003.0052-1 | H47: 1996-0.029.325-2 | I47: DEFERIDO
A48: FL-0036 | B48: FL-040/1998 | D48: 1998 | E48: DAVILAR | F48: 299.003.0050-3, 299.003.0051-1, 299.003.0049-1, 299.003.0347-2, 299.003.0045-7, 299.003.0053-8, 299.003.0046-5, 299.003.0054-6, 299.003.0052-1 | H48: 1996-0.029.325-2 | I48: DEFERIDO
A49: FL-0037
A50: FL-0038 | B50: FL-031/1997 | D50: 1997 | E50: KAUFFMANN | F50: 299.009.0094-2/0028-8/0025-1 | G50: FARIA LIMA | H50: 13-000.454-96*81 | I50: DEFERIDO
A51: FL-0039 | B51: FL-078/1997 | D51: 1997 | E51: SAINT PATICK | F51: 083.197.0067-1, 083.197.0068-1, 083.197.0069-8, 083.197.0065-5, 083.197.0066-3 | G51: FARIA LIMA | H51: 1996-0.029.348-1 | I51: DEFERIDO
A52: FL-0039 | B52: FL-032/1998 | D52: 1998 | E52: ETROS | F52: 083.197.0067-1, 083.197.0068-1, 083.197.0069-8, 083.197.0065-5, 083.197.0066-3 | G52: FARIA LIMA | H52: 1996-0.029.348-1 | I52: DEFERIDO
A53: FL-0040 | B53: FL-016/1998 | D53: 1998 | E53: CARMEM LINDA | F53: 083.007.0019-6 | G53: PINHEIROS | H53: 1996-0.029.381-3 | I53: DEFERIDO
A54: FL-0041 | B54: FL-003/2000 | D54: 2000 | E54: ALBERTO FORTE | F54: 299.023.0077-2; 299.023.0082-9 | H54: 1996-0.029.387-2 | I54: DEFERIDO
A55: FL-0042
A56: FL-0043
A57: FL-0044 | B57: FL-057/1997 | D57: 1997 | E57: RESULT | F57: 041.287.0038-1 | G57: HELIO PELEGRINO | H57: 13-000.608-96*53 | I57: DEFERIDO
A58: FL-0045
A59: FL-0046 | B59: FL-067/1997 | D59: 1997 | E59: RAFIC FARKOUH | F59: 041.036.0013-6/0019-5/0020-9 | G59: HELIO PELEGRINO | H59: 1996-0.029.476-3 | I59: DEFERIDO
A60: FL-0047
A61: FL-0048 | B61: FL-009/1998 | D61: 1998 | E61: AMERICO FERNANDO | F61: 041.079.0067-3 | G61: HELIO PELEGRINO | H61: 1996-0.029.505-0 | I61: DEFERIDO
A62: FL-0049
A63: FL-0050 | B63: FL-102/1997 | D63: 1997 | E63: TECNISA | F63: 041.288.0001-5 | G63: HELIO PELEGRINO | H63: 1996-0.029.530-1 | I63: DEFERIDO
A64: FL-0050 | B64: FL-012/1999 | D64: 1999 | E64: RESULT | F64: 041.288.0001-5 (antigo) e 041.288.0026-0 (atual) | G64: HELIO PELEGRINO | H64: 1996-0.029.530-1 | I64: DEFERIDO
A65: FL-0050 | B65: FL-036/2000 | D65: 2000 | E65: RESULT | F65: 041.288.0001-5 | G65: HELIO PELEGRINO | H65: 1996-0.029.530-1 | I65: DEFERIDO
A66: FL-0051 | B66: FL-016/1999 | D66: 1999 | E66: MARIO TEIXEIRA | F66: 299.020.0136-8 | G66: FARIA LIMA | H66: 1996-0.029.534-4 | I66: DEFERIDO
A67: FL-0052 | B67: FL-081/1997 | D67: 1997 | E67: KAUFFMANN | F67: 299.015.0252-5 | G67: FARIA LIMA | H67: 1996-0.029.543-3 | I67: DEFERIDO
A68: FL-0053 | B68: FL-099/1997 | D68: 1997 | E68: SEISA MESTER | F68: 299.095.0002-5, 299.095.0049-1, 299.095.0050-5 | G68: HELIO PELEGRINO | H68: 1996-0.029.553-0 | I68: DEFERIDO
A69: FL-0054 | B69: FL-039/1998 | D69: 1998 | E69: JACQUES DUVAL | F69: 083.054.0172-3 | G69: FARIA LIMA | H69: 1996-0.029.558-1 | I69: DEFERIDO
A70: FL-0055
A71: FL-0056 | B71: FL-129/1997 | D71: 1997 | E71: ZABO | F71: 041.288.0002-3, 041.288.0005-8, 041.288.0006-6, 041.288.0017-1, 041.288.0008-2, 041.288.0007-4, 046.211.0001-7 | G71: HELIO PELEGRINO | H71: 1996-0.029.626-0 | I71: DEFERIDO
A72: FL-0057
A73: FL-0058
A74: FL-0059 | B74: FL-077/1997 | D74: 1997 | E74: INPAR | F74: 299.028.0463-0 | H74: 1997-0.019.902-9 | I74: DEFERIDO
A75: FL-0060 | B75: FL-013/1998 | D75: 1998 | E75: BRAZIL REALTY | F75: 016.137.0039-3, 016 137.0054-7, 016.137.0055-5, 016.137.0111-1 | G75: HELIO PELEGRINO | H75: 1997-0.019.968-1 | I75: DEFERIDO
A76: FL-0061 | B76: FL-133/1997 | D76: 1997 | E76: INPAR | F76: 041.038.0027-5 | G76: HELIO PELEGRINO | H76: 1997-0.020.005-1 | I76: DEFERIDO
A77: FL-0062 | B77: FL-034/1998 | D77: 1998 | E77: PARINCORP | F77: 299.020.0156-2, 299.020.0123-6, 299.020.0111-2, 299.020.0112-0, 299.020.0115-5, 299.020.0116-3, 299.020.0117-1, 299.020.0118-1, 299.020.0114-7, 299.020.0113-9, 299.020.0105-8, 299.020.0106-6, 299.020.0107-4, 299.020.0110-4, 299.020.0119-8, 299.020.0120-1, 299.020.0121-1, 299.020.0122-8, 299.020.0124-4, 299.020.0145-7, 299.020.0064-7, 299.020.0063-3 | G77: FARIA LIMA | H77: 1997-0.104.439-8 | I77: DEFERIDO
A78: FL-0063 | B78: FL-142/1997 | D78: 1997 | E78: ZULMIRA E SERPLAN | F78: 083 015.0008-5, 083.015.0009-3 | G78: PINHEIROS | H78: 1997-0.106.370-8 | I78: DEFERIDO
A79: FL-0064
A80: FL-0065 | B80: FL-035/1998 | D80: 1998 | E80: MIGUEL HERVINGTON | F80: 083.178.0063-6, 083.178.0040-7, 083.178.0108-1 | G80: FARIA LIMA | H80: 1997-0.145.963-6 | I80: DEFERIDO
A81: FL-0066 | B81: FL-031/2000 | D81: 2000 | E81: KAUFFMANN | F81: 041.038.0017-8, 041.038.0018-6, 041.038.0019-4, 041.038.0021-6 | H81: 1997-0.172.991-9 | I81: DEFERIDO
A82: FL-0067 | B82: FL-042/1998 | D82: 1998 | E82: ETROS | F82: 083.197.0067-1, 083.197.0068-1, 083.197.0069-8, 083.197.0065-5, 083.197.0066-3 | H82: 1997-0.179.504-0 | I82: DEFERIDO
A83: FL-0068
A84: FL-0069 | B84: FL-005/1999 | D84: 1999 | E84: JORGE YUNES | F84: 083.067.0078-3 | G84: FARIA LIMA | H84: 1997-0.217.138-5 | I84: DEFERIDO
A85: FL-0070 | B85: FL-017/1998 | D85: 1998 | E85: JAFET TOMMASI | F85: 041.036.0045-4 | G85: HELIO PELEGRINO | H85: 1997-0.221.044-5 | I85: DEFERIDO
A86: FL-0071
A87: FL-0072
A88: FL-0073
A89: FL-0074
A90: FL-0075 | B90: FL-010/1999 | D90: 1999 | E90: ENGEDISA | F90: 041.080.0013-7/ 041.080.0021-8/ 041.080.0022- 6/ 041.080.0023-4/ 041.080.0024-2 | G90: HELIO PELEGRINO | H90: 1997-0.250.151-2 | I90: DEFERIDO
A91: FL-0076
A92: FL-0077 | B92: FL-045/1998 | D92: 1998 | E92: KAUFFMANN | F92: 299.015.0083-2, 299.015.0084-0, 299.015.0085-9, 299.015.0086-7, 299.015.0102-2, 299.015.0103-0, 299.015.0011-5 | H92: 1998-0.013.404-2 | I92: DEFERIDO
A93: FL-0078 | B93: FL-018/1999 | D93: 1999 | E93: COMERC. EMPREEN. BASIL | F93: 015.093.0004-1 | G93: PINHEIROS | H93: 1998-0.023.570-1 | I93: DEFERIDO
A94: FL-0079 | B94: FL-002/1999 | D94: 1999 | E94: ITAU | F94: 299.099.0273-5 | H94: 1998-0.035.933-8 | I94: DEFERIDO
A95: FL-0080 | B95: FL-023/1999 | D95: 1999 | E95: INPAR | F95: 299.056.0001-7 | H95: 1998-0.037.859-6 | I95: DEFERIDO
A96: FL-0081
A97: FL-0082 | B97: FL-043/1998 | D97: 1998 | E97: ARLETTE CICERO | F97: 083.015.0004-2 | G97: PINHEIROS | H97: 1998-0.047.606-7 | I97: DEFERIDO
A98: FL-0083 | B98: FL-044/1998 | D98: 1998 | E98: JAIR MARTINS | F98: 083.016.0008-1, 083.016.0009-8 | G98: PINHEIROS | H98: 1998-0.068.877-3 | I98: DEFERIDO
A99: FL-0084 | B99: FL-008/1999 | D99: 1999 | E99: AURY | F99: 083.195.0021-4/ 0022-2/ 0028-1/ 0029-1/ 0068-0/ 0069-9/ 0070-2/ 0071-0 | G99: FARIA LIMA | H99: 1998-0.069.392-0 | I99: DEFERIDO
A100: FL-0085 | B100: FL-001/1999 | D100: 1999 | E100: SANTA PAULA | F100: 299.117.0123-7/0002-8/0057-5/ 0224-1 | H100: 1998-0.073.783-9 | I100: DEFERIDO
...

Sheet 2_CONTROLE_ESTOQUE
A1: CODIGO | B1: LEI | C1: PA (16 digitos) | D1: PA (12 digitos) | E1: DATA AUTUACAO PA | F1: STATUS PA | G1: INTERESSADO | H1: CNPJ | I1: CPF | J1: ENDEREÇO | K1: SETOR OUC | L1: REQUERIMENTO | M1: CONTRIBUINTE - SQ | N1: CONTRIBUINTE - L | O1: ÁREA DO TERRENO | P1: USO DA ACA | Q1: ACA-R (REAL) | R1: ACA-R BENEFICIOS | S1: ACA-R | T1: ACA-NR (REAL) | U1: ACA-NR (BENEFÍCIOS) | V1: ACA-NR | W1: ACA-TOTAL | X1: TIPO DE CONTRAPARTIDA | Y1: VALOR R$ | Z1: CEPAC ACA | AA1: CEPAC PARAMETROS | AB1: TOTAL CEPAC | AC1: CERTIDAO | AD1: SITUACAO | AE1: DATA CERTIDAO | AF1: NUVEM m² - R | AG1: NUVEM m² -nR | AH1: NUVEM m² | AI1: NUVEM CEPAC | AJ1: OBS | AK1: RESP/DATA
A2: FL-0095 | B2: 13.769/2004 | D2: 2013-0325611-4 | E2: 41579 | F2: DEFERIDO | G2: SAO JOSE DESENVOLVIMENTO IMOBILIARIO 33 LTDA. | H2: 10174781/0001-94; | J2: RUA FREDERIC CHOPIN, 20; | K2: FARIA LIMA | L2: VINCULACAO | M2: 083207; | N2: 0135-1; | O2: 287.82 | P2: R | Q2: 863.46 | W2: =T2+Q2 -> 863.46 | X2: CEPAC (título) | Z2: 785 | AB2: =AA2+Z2 -> 785 | AC2: FL-001/2014 | AD2: VALIDA | AE2: 41645 | AJ2: CERTIDÃO 04/12/SMDU/CTLU | AK2: AMANDA/08/07/2025
A3: FL-0148 | B3: 13.769/2004 | D3: 2005-0320407-9 | E3: 38702 | F3: DEFERIDO | G3: CONCEITO CONSTRUTORA E PARTICIPACOES LTDA. | H3: 71657464/0001-13; | J3: AVENIDA BRIGADEIRO FARIA LIMA; RUA TABAPUA; RUA JOSE GONCALVES OLIVEIRA | K3: HÉLIO PELEGRINO | L3: VINCULACAO | M3: 229008; | N3: 0075-1; 0027-1; 0024-7; 0025-8; 0023-9; 0026-9; 0022-0; 0021-2; 0019-0; 0043-3; 0076-1; 0077--8; 0014-6; | O3: 2878.34 | P3: NR | T3: 780.87 | W3: =T3+Q3 -> 780.87 | X3: CEPAC (título) | Z3: 975 | AA3: 173 | AB3: =AA3+Z3 -> 1148 | AC3: FL-004/2006 | AD3: VALIDA | AE3: 39016 | AJ3: CERTIDÃO COMPLEMENTAR (DE QUAL?) | AK3: AMANDA/08/07/2025
A4: FL-0211 | B4: 13.769/2004 | D4: 2003-0295416-0 | E4: 37937 | F4: DEFERIDO | G4: VR EMPREENDIMENTOS PARTICIPACOES E SERVICOS; SAINT PATRICK INCORPORADORA E PARTICIPACOES LTDA; SANTA CRUZ FOMENTO COMERCIAL LTDA.; CINCINATI HOLDINGS LTDA.; ESCALA EMPREENDIMENTOS E PARTICIPACOES LTDA.; VISBELA EMPREENDIMENTOS E PARTICIPACOES LTDA.; BANDO BMD LTDA.; | H4: 01150594/0001-80; 97355069/0001-70; 50117142/0001-01; 09092729/0001-00; 00338747/0001-54; 04036914/0001-63; 60892304/0001-32; | J4: AVENIDA BRIGADEIRO FARIA LIMA; | L4: VINCULACAO | M4: 015057; | N4: 0009-4; | O4: 9372 | W4: =T4+Q4 -> 0 | X4: CEPAC (título) | AA4: 2343 | AB4: =AA4+Z4 -> 2343 | AC4: FL-022/2010 | AD4: CANCELADA | AE4: 40456 | AK4: AMANDA/08/07/2025
A5: FL-0211 | B5: 13.769/2004 | D5: 2014-0161140-7 | E5: 41799 | F5: DEFERIDO | G5: VR EMPREENDIMENTOS PARTICIPACOES E SERVICOS; SAINT PATRICK INCORPORADORA E PARTICIPACOES LTDA; SANTA CRUZ FOMENTO COMERCIAL LTDA.; CINCINATI HOLDINGS LTDA.; ESCALA EMPREENDIMENTOS E PARTICIPACOES LTDA.; VISBELA EMPREENDIMENTOS E PARTICIPACOES LTDA.; BANDO BMD LTDA.; | H5: 01150594/0001-80; 97355069/0001-70; 50117142/0001-01; 09092729/0001-00; 00338747/0001-54; 04036914/0001-63; 60892304/0001-32; | J5: AVENIDA BRIGADEIRO FARIA LIMA; | L5: DESVINCULACAO | M5: 015057; | N5: 0009-4; | O5: 9372 | W5: =T5+Q5 -> 0 | X5: CEPAC (título) | AA5: 2343 | AB5: =AA5+Z5 -> 2343 | AC5: DV-001/2015 | AD5: VALIDA | AE5: 42095
A6: FL-0217 | B6: 13.769/2004 | D6: 2003-0324486-7 | E6: 37967 | F6: DEFERIDO | G6: BL EMPREENDIMENTOS SPE LTDA | H6: 07467969/0001-16; | J6: RUA DOUTOR RENATO PAES DE BARROS; RUA BENEDITO LAPIN; | K6: HÉLIO PELEGRINO | L6: VINCULACAO | M6: 016166; | N6: 0018-7; 0019-5; 0020-9; 0021-7; 0042-1; | O6: 1600 | P6: R | Q6: 4800 | W6: =T6+Q6 -> 4800 | X6: CEPAC (título) | Z6: 1920 | AB6: =AA6+Z6 -> 1920 | AC6: FL-001/2006 | AD6: VALIDA | AE6: 38764 | AK6: PRISCILA/12/05/2025
A7: FL-0218 | B7: 13.769/2004 | D7: 2003-0325166-9 | E7: 37970 | F7: DEFERIDO | G7: BOLSA DE IMÓVEIS DESENVOLVIMENTO IMOBILIÁRIO LTDA; TECNUM & CORPORATE EMPREENDIMENTOS IMOBILIÁRIOS LTDA; QUALITY BUILDING EMPREENDIMENTOS E PARTICIPAÇÕES LTDA | H7: 04913697/0001-42;64596046/0001-00;01490046/0001-07 | J7: RUA LEOPOLDO COUTO DE MAGALHÃES JUNIOR, 1.387 | K7: FARIA LIMA | L7: VINCULACAO | M7: 299019; | N7: 0084-9; 0085-7; 0080-6; 0051-2; 0004-0; 0062-8; | O7: 1646.88 | P7: R | Q7: 4940.97 | W7: =T7+Q7 -> 4940.97 | X7: CEPAC (título) | Z7: 3801 | AB7: =AA7+Z7 -> 3801 | AC7: FL-012/2007 | AD7: VALIDA | AE7: 39349 | AK7: LUCIANA/16/05/2025
A8: FL-0221 | B8: 13.769/2004 | C8: 7810.2020/0001473-9 | F8: DEFERIDO | G8: RAUL SABBAGA CHEDE | J8: RUA CANÁRIO; RUA INHAMBU; RUA CORONEL HUMAITÁ | K8: HÉLIO PELEGRINO | L8: VINCULACAO | M8: 041038; | N8: 0022-4; 0028-3; 0033-1; 0036-4; 0050-1; 0051-8; 0052-6 | O8: 6245.44 | P8: R | W8: =T8+Q8 -> 0 | X8: CEPAC (título) | Z8: 8070 | AB8: =AA8+Z8 -> 8070 | AD8: VALIDA | AE8: 38330 | AJ8: PROCESS INICIAL 2003-0.327.160-0 - CERTIDÃO 24//04/SEMPLA - EMITIDA POR SEMPLA - PAGTO PARTE CONTRAPARTIDA FINANCEIRA - PARTE CEPAC - | AK8: LUCIANA/16/05/2025
A9: FL-0230 | B9: 13.769/2004 | D9: 2004-0096854-8 | E9: 38093 | F9: DEFERIDO | G9: ATALANTA PARTICIPAÇÕES E PROPRIEDADES LTDA | H9: 04791780/0001-96; | J9: RUA IRACI, 707; ESQUINA COM A RUA HUNGRIA | K9: FARIA LIMA | L9: VINCULACAO | M9: 083231; | N9: 0049-7; 0050-0; 0051-9; 0052-7; 0053-5; 0054-3; 0055-1; 0056-1; 0057-8; 0058-6; 0059-4; 0060-8 | O9: 684.7 | P9: NR | T9: 2033 | W9: =T9+Q9 -> 2033 | X9: OODC (dinheiro) | Y9: 2365682 | AB9: =AA9+Z9 -> 0 | AD9: VALIDA | AE9: 38260 | AJ9: Pago R$ 2.365.682,00, conforme despacho da CTLU CERTIDÃO 17/04/SEMPLA | AK9: LUCIANA/16/05/2025
A10: FL-0235 | B10: 13.769/2004 | D10: 2004-0294005-5 | E10: 38336 | F10: DEFERIDO | G10: PALMARES EMPREENDIMENTOS E PARTICIPAÇÕES S/A | H10: 47218250/0001-66; | J10: AVENIDA BRIGADEIRO FARIA LIMA, 173; AVENIDA PEDROSO DE MORAES, 1.271 E 1.323 | K10: PINHEIROS | L10: VINCULACAO | M10: 083007; | N10: 0040-4; 0044-7; 0046-3; | O10: 2862.48 | P10: NR | W10: =T10+Q10 -> 0 | X10: CEPAC (título) | AA10: 254 | AB10: =AA10+Z10 -> 254 | AC10: FL-010/2009 | AD10: VALIDA | AE10: 39888 | AK10: LUCIANA/16/05/2025
A11: FL-0236 | B11: 13.769/2004 | D11: 2005-0022151-7 | E11: 38385 | F11: DEFERIDO | G11: DESTINY DE PARTICIPAÇÃO LTDA | H11: 05574820/0001-00; | J11: RUA CORONEL ARTHUR DE PAULA FERREIRA, 185, 191, 195, 203, 209, 215, 227, 237; RUA MONTE APRAZÍVEL, 410, 416 | K11: HÉLIO PELEGRINO | L11: VINCULACAO | M11: 041282; | N11: 0030-1; 00031-1; 0004-2; 0101-4; | O11: 1767 | P11: R | Q11: 1185 | W11: =T11+Q11 -> 1185 | X11: CEPAC (título) | Z11: 790 | AB11: =AA11+Z11 -> 790 | AC11: FL-008/2009 | AD11: VALIDA | AE11: 39874 | AK11: LUCIANA/16/05/2025
A12: FL-0237 | B12: 13.769/2004 | D12: 2004-0299325-6 | E12: 38344 | F12: DEFERIDO | G12: FADLO HAIDAR EMPREENDIMENTO IMOBILIÁRIO SPE LTDA | H12: 08541185/0001-53; | J12: RUA FADLO AIDAR | K12: HÉLIO PELEGRINO | L12: VINCULACAO | M12: 299077; | N12: 0264-1; | O12: 2443.3 | P12: R | Q12: 4886.6 | W12: =T12+Q12 -> 4886.6 | X12: CEPAC (título) | Z12: 1955 | AB12: =AA12+Z12 -> 1955 | AC12: FL-017/2008 | AD12: VALIDA | AE12: 39764 | AK12: LUCIANA/16/05/2025
A13: FL-0238 | B13: 13.769/2004 | D13: 2004-0158467-0 | E13: 38163 | F13: DEFERIDO | G13: NAÇÕES UNIDAS EMPREENDIMENTO IMOBILIÁRIO LTDA | H13: 05095230/0001-03; | J13: rua gomes de carvalho, 1996 | K13: FARIA LIMA | L13: VINCULACAO | M13: 299038; | N13: 0008-6; 0009-4; 0020-5; 0040-1; | O13: 5796.4 | P13: NR | T13: 17389.2 | W13: =T13+Q13 -> 17389.2 | X13: CEPAC (título) | Z13: 19322 | AA13: 773 | AB13: =AA13+Z13 -> 20095 | AC13: FL-002/2008 | AD13: VALIDA | AE13: 39525 | AK13: LUCIANA/16/05/2025
A14: FL-0242 | B14: 13.769/2004 | D14: 2007-0186164-5 | E14: 39245 | F14: DEFERIDO | G14: WTORRE CJ EMPREENDIMENTO IMOBILIARIO S/A. | H14: 59535849/0001-02; | J14: AVENIDA NAÇÕES UNIDAS ESQUINA COM RUA EUGENIO DE MEDEIROS | K14: PINHEIROS | L14: VINCULACAO | M14: 083103; | N14: 0064-6; | O14: 8457.39 | P14: NR | T14: 14386.38 | W14: =T14+Q14 -> 14386.38 | X14: CEPAC (título) | Z14: 8463 | AB14: =AA14+Z14 -> 8463 | AC14: FL-017/2007 | AD14: VALIDA | AE14: 39433 | AK14: AMANDA/13/05/2025
A15: FL-0245 | B15: 13.769/2004 | D15: 2007-0337168-8 | E15: 39384 | F15: DEFERIDO | G15: CICLAME INCORPORADORA LTDA; ASTROEMERIA INCORPORADORA LTDA; | H15: 07697863/0001-09; 07698130/0001-99 | J15: RUA CLAUDIO SOARES E RUA VALERIO DE CARVALHO | K15: PINHEIROS | L15: VINCULACAO | M15: 015073; | N15: 0120-0; 0067-0; 0078-6; 0084-0; 0085-9; | O15: 5266.57 | P15: NR | W15: =T15+Q15 -> 0 | X15: CEPAC (título) | AA15: 453 | AB15: =AA15+Z15 -> 453 | AC15: FL-002/2010 | AD15: VALIDA | AE15: 40185 | AJ15: COMPLEMENTA CERTIDÕES 112/97/SEMPLA - ACA DE 13.493,442 - Certidão 05/10/CTLU (Consumo de ACA) | AK15: AMANDA/13/05/2025
A16: FL-0247 | B16: 13.769/2004 | D16: 2008-0090243-9 | E16: 39531 | F16: DEFERIDO | G16: JORGE THOMAZ WEIL; PEDRO SYLVIO WEIL | I16: 678506778-20; 039696658-68; | J16: RUA DIOGO MOREIRA, 75 E 87 | K16: PINHEIROS | L16: VINCULACAO | M16: 015092; | N16: 0034-7; 0009-6; | O16: 621.11 | P16: NR | T16: 1863.33 | W16: =T16+Q16 -> 1863.33 | X16: CEPAC (título) | Z16: 1036 | AB16: =AA16+Z16 -> 1036 | AC16: FL-006/2009 | AD16: VALIDA | AE16: 39871 | AK16: AMANDA/13/05/2025
A17: FL-0248 | B17: 13.769/2004 | D17: 2005-0014951-4 | E17: 38376 | F17: DEFERIDO | G17: FVM DESENVOLVIMENTO IMOBILIARIO LTDA. | H17: 08169300/0001-00; | J17: RUA ALVORADA | K17: HÉLIO PELEGRINO | L17: VINCULACAO | M17: 299177; | N17: 0072-9; 0070-2; 0036-2; | O17: 800 | P17: R | Q17: 2400 | W17: =T17+Q17 -> 2400 | X17: CEPAC (título) | Z17: 960 | AA17: 70 | AB17: =AA17+Z17 -> 1030 | AC17: FL-014/2009 | AD17: VALIDA | AE17: 40008 | AJ17: QUANTIDADE DE CEPAC PARA ACA E PARÂMETROS EXTRAÍDO DA PLANILHA PUBLICADA | AK17: AMANDA/13/05/2025
A18: FL-0253 | B18: 13.769/2004 | C18: 7810.2022/0001829-0 | F18: DEFERIDO | G18: 2509 FUNDO DE INVESTIMENTO IMOBILIÁRIO – FII; ADMINISTRADORA PMV LTDA; | H18: 19419994/0001-03; 05083840/0001-89; | J18: RUA FUNCHAL 160; AVENIDA CHEDID JAFET 75; AVENIDA PRESIDENTE JUSCELINO KUBITSCHECK 1909; RUA PEQUETIBA, 170; | K18: OLIMPÍADAS | L18: VINCULACAO | M18: 299027; | N18: 0006-1; | O18: 38803.44 | P18: R | Q18: 1074.86 | W18: =T18+Q18 -> 1074.86 | X18: CEPAC (título) | Z18: 0 | AA18: 0 | AB18: =AA18+Z18 -> 0 | AC18: FL-001/2024 | AD18: VALIDA | AE18: 45517 | AK18: PRISCILA/11/09/2025
A19: FL-0302 | B19: 13.769/2004 | D19: 2005-0020668-2 | E19: 38384 | F19: DEFERIDO | G19: EVEN CONSTRUTORA E INCORPORADORA LTDA; PINHEIROS DESENVOLVIMENTO IMOBILIARIO LTDA; | H19: 43470988/0001-65; 07241467/0001-72; | J19: RUA FREDERICO HERMANN JUNIOR; RUA NICOLAU GAGLIARDI | K19: PINHEIROS | L19: VINCULACAO | M19: 083233; | N19: 0004-2; | O19: 7589.9 | P19: R | Q19: 22769.7 | W19: =T19+Q19 -> 22769.7 | X19: CEPAC (título) | Z19: 8133 | AB19: =AA19+Z19 -> 8133 | AC19: FL-002/2006 | AD19: VALIDA | AE19: 38786 | AK19: AMANDA/13/05/2025
A20: FL-0303 | B20: 13.769/2004 | D20: 2005-0020911-8 | E20: 38354 | F20: DEFERIDO | G20: CIPESA ENGENHARIA S/A | H20: 12272753/0001-32; | J20: RUA BENEDITO LAPIN; RUA BANDEIRA PAULISTA; | K20: HÉLIO PELEGRINO | L20: VINCULACAO | M20: 016167; | N20: 0091-2; 0090-4; 0089-0; 0088-2; 0087-4; 0131-5; 0132-3; | O20: 1404.76 | P20: R | Q20: 4212.33 | W20: =T20+Q20 -> 4212.33 | X20: CEPAC (título) | Z20: 1685 | AB20: =AA20+Z20 -> 1685 | AC20: FL-006/2006 | AD20: VALIDA | AE20: 39050 | AK20: GIULIA/13/05/2025
A21: FL-0304 | B21: 13.769/2004 | D21: 2005-0021493-6 | E21: 38385 | F21: DEFERIDO | G21: QUEIROZ GALVAO CYRELA EMPREENDIMENTOS E PARTICIPACOES S/A | H21: 06878430/0001-97; | J21: RUA HORACIO LAFER, 120; | K21: HÉLIO PELEGRINO | L21: VINCULACAO | M21: 299014; | N21: 0014-5;0016-1;0019-6; 0099-6; 0100-1; | O21: 2375 | P21: R | Q21: 7125 | W21: =T21+Q21 -> 7125 | X21: CEPAC (título) | Z21: 2850 | AB21: =AA21+Z21 -> 2850 | AC21: FL-003/2006 | AD21: VALIDA | AE21: 38897 | AK21: GIULIA/13/05/2025
A22: FL-0305 | B22: 13.769/2004 | D22: 2005-0256976-6 | E22: 38643 | F22: DEFERIDO | G22: F. REIS ADMINISTRACAO DE IMOVEIS LTDA | H22: 00076468/0001-60; | J22: RUA DAS OLIMPIADAS, 242; | K22: OLIMPÍADAS | L22: VINCULACAO | M22: 299050; | N22: 0085-0; | O22: 1040 | P22: NR | T22: 2079.1 | W22: =T22+Q22 -> 2079.1 | X22: CEPAC (título) | Z22: 2311 | AB22: =AA22+Z22 -> 2311 | AC22: FL-005/2006 | AD22: VALIDA | AE22: 39016 | AK22: GIULIA/13/05/2025
A23: FL-0306 | B23: 13.769/2004 | D23: 2005-0324078-4 | E23: 38707 | F23: DEFERIDO | G23: BOLSA DE IMOVEIS DESENVOLVIMENTO IMOBILIARIO LTDA | H23: 04913697/0001-42; | J23: RUA LEOPOLDO COUTO DE MAGALHAES JUNIOR, 1.151; | K23: FARIA LIMA | L23: VINCULACAO | M23: 299020; | N23: 0026-4; 0140-6; 0150-3; | O23: 1500 | P23: R | Q23: 4500 | W23: =T23+Q23 -> 4500 | X23: CEPAC (título) | Z23: 3462 | AB23: =AA23+Z23 -> 3462 | AC23: FL-008/2007 | AD23: VALIDA | AE23: 39254 | AK23: GIULIA/13/05/2025
A24: FL-0308 | B24: 13.769/2004 | D24: 2006-0079215-0 | E24: 38798 | F24: DEFERIDO | G24: BRALDECAR EMPREENDIMENTOS LTDA | H24: 55033252/0001-09; | J24: AVENIDA PRESIDENTE JUSCELINO KUBITSCHEK, 1327; | K24: OLIMPÍADAS | L24: ALTERACAO | M24: 299028; | N24: 0478-9; | O24: 4475 | P24: NR | T24: 13425 | W24: =T24+Q24 -> 13425 | X24: CEPAC (título) | Z24: 14917 | AB24: =AA24+Z24 -> 14917 | AC24: FL-014/2007 | AD24: VALIDA | AE24: 39399 | AJ24: CANCELA A CERTIDÃO FL-010/2007 | AK24: GIULIA/13/05/2025
A25: FL-0308 | B25: 13.769/2004 | D25: 2006-0079215-0 | E25: 38798 | F25: DEFERIDO | G25: BRALDECAR EMPREENDIMENTOS LTDA | H25: 55033252/0001-09; | J25: AVENIDA PRESIDENTE JUSCELINO KUBITSCHEK, 1327; | K25: OLIMPÍADAS | L25: VINCULACAO | M25: 299028; | N25: 0478-9; | O25: 4475 | P25: NR | T25: 13425 | W25: =T25+Q25 -> 13425 | X25: CEPAC (título) | Z25: 11127 | AB25: =AA25+Z25 -> 11127 | AC25: FL-010/2007 | AD25: CANCELADA | AE25: 39310 | AJ25: CANCELADA PELA CERTIDÃO FL014/2007 | AK25: GIULIA/13/05/2025
A26: FL-0314 | B26: 13.769/2004 | D26: 2007-0139265-3 | E26: 39198 | F26: DEFERIDO | G26: KALAPALO EMPREENDIMENTOS IMOBILIÁRIOS LTDA; GLIESE INCOPORADORA LTDA | H26: 07936960/0001-07; 08352433/0001-13; | J26: RUA INHAMBU; AVEMIDA JURITI; AVENIDA HÉLIO PELEGRINO; RUA TUIM; | K26: HÉLIO PELEGRINO | L26: VINCULACAO | M26: 041063; | N26: 0004-4; 0005-2; 0003-6; 0002-8; 0023-0; | O26: 6865 | P26: R | Q26: 20584.62 | W26: =T26+Q26 -> 20584.62 | X26: CEPAC (título) | Z26: 13530 | AB26: =AA26+Z26 -> 13530 | AC26: FL-008/2010 | AD26: VALIDA | AE26: 40261 | AK26: VITOR/15/05/2025
A27: FL-0314 | B27: 13.769/2004 | D27: 2007-0139265-3 | E27: 39198 | F27: DEFERIDO | G27: KALAPALO EMPREENDIMENTOS IMOBILIÁRIOS LTDA; GLIESE INCOPORADORA LTDA | H27: 07936960/0001-07; 08352433/0001-13; | J27: RUA INHAMBU; AVEMIDA JURITI; AVENIDA HÉLIO PELEGRINO; RUA TUIM; | K27: HÉLIO PELEGRINO | L27: VINCULACAO | M27: 041063; | N27: 0004-4; 0005-2; 0003-6; 0002-8; 0023-0; | O27: 6865 | P27: R | W27: =T27+Q27 -> 0 | X27: CEPAC (título) | AA27: 4554 | AB27: =AA27+Z27 -> 4554 | AC27: FL-008/2008 | AD27: VALIDA | AE27: 39609 | AK27: VITOR/15/05/2025
A28: FL-0315 | B28: 13.769/2004 | D28: 2007-0179306-2 | E28: 39237 | F28: DEFERIDO | G28: CAPH INCORPORADORA LTDA | H28: 08701394/0001-17; | J28: AVENIDA DOUTOR CARDOSO DE MELO Nº 585 | K28: HÉLIO PELEGRINO | L28: VINCULACAO | M28: 299104; | N28: 0027-6; 0025-1; 0024-1; 0065-9; 0066-7; 0067-5; 0116-7; 0113-2; 0051-9; 0052-7; 0070-5; 0115-9; | O28: 5800 | P28: R | Q28: 15501.12 | W28: =T28+Q28 -> 15501.12 | X28: CEPAC (título) | Z28: 5737 | AB28: =AA28+Z28 -> 5737 | AC28: FL-011/2008 | AD28: VALIDA | AE28: 39696 | AK28: VITOR/15/05/2025
A29: FL-0316 | B29: 13.769/2004 | D29: 2007-0235144-6 | E29: 39288 | F29: DEFERIDO | G29: CETUS EVEN EMPREENDIMENTOS IMOBILIÁRIOS LTDA | H29: 08747241/0001-00; | J29: RUA ARAGUARI Nº 472 | K29: HÉLIO PELEGRINO | L29: VINCULACAO | M29: 041078; | N29: 0087-3; 0026-1; 0025-3; 0054-7; | O29: 1641.4 | P29: R | Q29: 4915.4 | W29: =T29+Q29 -> 4915.4 | X29: CEPAC (título) | Z29: 4372 | AB29: =AA29+Z29 -> 4372 | AC29: FL-016/2007 | AD29: VALIDA | AE29: 39423 | AK29: VITOR/15/05/2025
A30: FL-0317 | B30: 13.769/2004 | D30: 2008-0078866-0 | E30: 39519 | F30: DEFERIDO | G30: F. REIS ADMINISTRAÇÃO DE IMÓVEIS LTDA | H30: 00076468/0001-60; | J30: AVENIDA DOUTOR CARDOSO DE MELO Nº 1038 | K30: OLIMPÍADAS | L30: VINCULACAO | M30: 299080; | N30: 0079-7; 0004-5; | O30: 1000 | P30: NR | T30: 2000 | W30: =T30+Q30 -> 2000 | X30: CEPAC (título) | Z30: 2167 | AB30: =AA30+Z30 -> 2167 | AC30: FL-009/2008 | AD30: VALIDA | AE30: 39624 | AK30: VITOR/15/05/2025
A31: FL-0318 | B31: 13.769/2004 | C31: 7810.2022/0000813-9 | E31: 43714 | F31: DEFERIDO | G31: FLPP FARIA LIMA PRIME PROPERTIES S/A | H31: 07349852/0001-38; | J31: AV. BRIGADEIRO FARIA LIMA, 3732 | K31: FARIA LIMA | L31: VINCULACAO | M31: 299020; | N31: 0269-0; | O31: 13458.64 | P31: NR | T31: 33109.95 | W31: =T31+Q31 -> 33109.95 | X31: CEPAC (título) | Z31: 47291 | AA31: 2775 | AB31: =AA31+Z31 -> 50066 | AC31: FL-007/2022 | AD31: VALIDA | AE31: 44772 | AK31: GIULIA/29/05/2025
A32: FL-0318 | B32: 13.769/2004 | C32: 7810.2019/0000820-6 | E32: 43714 | F32: DEFERIDO | G32: FLPP FARIA LIMA PRIME PROPERTIES S/A | H32: 07349852/0001-38; | J32: AV. BRIGADEIRO FARIA LIMA, RUA LEOPOLDO COUTO DE MAGALHÃES, RUA LÍCIO NOGUEIRA E RUA FERNANDES DE ABREU | K32: FARIA LIMA | L32: VINCULACAO | M32: 299020; | N32: 0037-1; 0039-6; 0053-1; 0045-0; 0060-4; 0040-1; 0038-8; 0236-4; 0170-8; 0141-4; 0164-3; 0166-1; 0036-1; 0268-2; | O32: 13034.02 | P32: NR | T32: 33109.96 | W32: =T32+Q32 -> 33109.96 | X32: CEPAC (título) | Z32: 47291 | AA32: 2775 | AB32: =AA32+Z32 -> 50066 | AC32: FL-006/2021 | AD32: CANCELADA | AE32: 44476 | AK32: GIULIA/29/05/2025
A33: FL-0318 | B33: 13.769/2004 | D33: 2007-0397221-5 | E33: 39444 | F33: DEFERIDO | G33: FLPP FARIA LIMA PRIME PROPERTIES S/A | H33: 07349852/0001-38; | J33: AV. BRIGADEIRO FARIA LIMA, RUA LEOPOLDO COUTO DE MAGALHÃES, RUA LÍCIO NOGUEIRA E RUA FERNANDES DE ABREU | K33: FARIA LIMA | L33: VINCULACAO | M33: 299020; | N33: 0037-1; 0039-6; 0053-1; 0045-0; 0060-4; 0040-1; 0038-8; 0236-4; 0170-8; 0141-4; 0164-3; 0166-1; 0036-1; 0268-2; | O33: 13034.02 | P33: NR | T33: 33109.96 | W33: =T33+Q33 -> 33109.96 | X33: CEPAC (título) | Z33: 47291 | AA33: 5014 | AB33: =AA33+Z33 -> 52305 | AC33: FL-008/2018 | AD33: CANCELADA | AE33: 43325 | AJ33: DUPLO CHECK SO VAI ATE ESTA CERTIDAO ( AS FL-006/2021 E FL-008/2018 NÃO APARECEM) | AK33: GIULIA/29/05/2025
A34: FL-0318 | B34: 13.769/2004 | D34: 2007-0397221-5 | E34: 39444 | F34: DEFERIDO | G34: FLPP FARIA LIMA PRIME PROPERTIES S/A | H34: 07349852/0001-38; | J34: AV. BRIGADEIRO FARIA LIMA, RUA LEOPOLDO COUTO DE MAGALHÃES, RUA LÍCIO NOGUEIRA E RUA FERNANDES DE ABREU | K34: FARIA LIMA | L34: VINCULACAO | M34: 299020; | N34: 0037-1; 0039-6; 0053-1; 0060-4; 0040-1; 0038-8; 0236-4; 0170-8; 0141-4; 0164-3; 0166-1; 0036-1; 0164-3; | O34: 12121.78 | P34: NR | T34: 33109.96 | W34: =T34+Q34 -> 33109.96 | X34: CEPAC (título) | Z34: 47899 | AA34: 2382 | AB34: =AA34+Z34 -> 50281 | AC34: FL-009/2014 | AD34: CANCELADA | AE34: 41894 | AK34: GIULIA/29/05/2025
A35: FL-0318 | B35: 13.769/2004 | D35: 2007-0397221-5 | E35: 39444 | F35: DEFERIDO | G35: FLPP FARIA LIMA PRIME PROPERTIES S/A, RANANA PARTICIPAÇÕES L TDA , EYRE EMPREENDIMENTOS E PARTICIPAÇÕES L TDA, CEFILI-CONSTRUÇÕES E ENGENHARIA L TDA; | H35: 07349852/0001-38; 04652521/0001-84; 05033236/0001-48; 61620654/0001-02; | J35: AV. BRIGADEIRO FARIA LIMA, RUA LEOPOLDO COUTO DE MAGALHÃES, RUA LÍCIO NOGUEIRA E RUA FERNANDES DE ABREU | K35: FARIA LIMA | L35: VINCULACAO | M35: 299020; | N35: 0037-1; 0053-1; 0060-4; 0040-1; 0038-8; 0170-8; 0141-4; 0164-3; 0078-7; 0163-5; 0082-5; 0081-0; 0080-9; 0079-5; 0132-5; 0039-6; 0045-0; 0052-3; 0168-6; 0136-8; 0135-1; 0134-1; 0003-5; 0153-8; 0006-1; 0008-6; 0092-2; 0093-0; 0137-6; 0138-4; | O35: 11748.75 | P35: NR | T35: 33109.96 | W35: =T35+Q35 -> 33109.96 | X35: CEPAC (título) | Z35: 2737 | AB35: =AA35+Z35 -> 2737 | AC35: FL-014/2010 | AD35: CANCELADA | AE35: 40319 | AJ35: Complementa a certidão FL-004/2009 | AK35: GIULIA/29/05/2025
A36: FL-0318 | B36: 13.769/2004 | D36: 2007-0397221-5 | E36: 39444 | F36: DEFERIDO | G36: FLPP EMPREENDIMENTOS IMOBILIÁRIOS S/A | H36: 07349852/0001-38; | J36: AV. BRIGADEIRO FARIA LIMA, RUA LEOPOLDO COUTO DE MAGALHÃES, RUA LÍCIO NOGUEIRA E RUA FERNANDES DE ABREU | K36: FARIA LIMA | L36: VINCULACAO | M36: 299020; | N36: 0037-1; 0053-1; 0060-4; 0040-1; 0038-8; 0078-7; 0163-5; 0082-5; 0081-0; 0080-9; 0079-5; 0132-5; 0039-6; 0045-0; 0052-3; 0168-6; 0136-8; 0135-1; 0134-1; 0003-5; 0153-8; 0006-1; 0008-6; 0092-2; 0093-0; 0137-6; 0138-4; | O36: 9352.25 | P36: NR | T36: 28056.75 | W36: =T36+Q36 -> 28056.75 | X36: CEPAC (título) | Z36: 45886 | AB36: =AA36+Z36 -> 45886 | AC36: FL-004/2009 | AD36: CANCELADA | AE36: 39862 | AK36: GIULIA/29/05/2025
A37: FL-0318 | B37: 13.769/2004 | D37: 2007-0397221-5 | E37: 39444 | F37: DEFERIDO | G37: FLPP SERVIÇOS DE COBRANÇA E DE INFORMAÇÕES CADASTRAIS | H37: 07349852/0001-38; | J37: AV. BRIGADEIRO FARIA LIMA, RUA LEOPOLDO COUTO DE MAGALHÃES, RUA LÍCIO NOGUEIRA E RUA FERNANDES DE ABREU | K37: FARIA LIMA | L37: VINCULACAO | M37: 299020; | N37: 0037-1; 0053-1; 0060-4; 0040-1; 0038-8; 0078-7; 0163-5; 0082-5; 0081-0; 0080-9; 0079-5; 0132-5; 0045-0; 0052-3; 0168-6; 0136-8; 0135-1; 0134-1; 0003-5; 0153-8; 0006-1; 0008-6; 0092-2; 0093-0; 0137-6; 0138-4; | O37: 9177.25 | P37: NR | T37: 27531.55 | W37: =T37+Q37 -> 27531.55 | X37: CEPAC (título) | Z37: 45886 | AB37: =AA37+Z37 -> 45886 | AC37: FL-001/2008 | AD37: CANCELADA | AE37: 39493 | AK37: GIULIA/29/05/2025
A38: FL-0319 | B38: 13.769/2004 | D38: 2010-0089023-2 | E38: 40267 | F38: DEFERIDO | G38: YUNY GTIS ATILIO INNOCENTI EMPREENDIMENTOS LTDA | H38: 09234157/0001-56; | J38: RUA PROFESSOR ATILIO INNOCENTI, 165 E 193, RUA LEOPOLDO COUTO MAGALHAES JUNIOR 797 E 807 E RUA BELCHIOR SOARES, 28, 40, 50, 56, 64, 68, 78, 187, 197, 225 E 237; | K38: HÉLIO PELEGRINO | L38: ALTERACAO | M38: 299021; | N38: 0135-4; 0133-8; 0061-7; 0060-9; 0062-5; 0064-1; 0066-8; 0067-6; 0068-4; 0069-2; 0071-4; 0072-2; 0070-6; 0065-1; 0063-3; | O38: 3669.12 | P38: NR | T38: 11007.36 | W38: =T38+Q38 -> 11007.36 | X38: CEPAC (título) | Z38: 9540 | AB38: =AA38+Z38 -> 9540 | AC38: FL-016/2010 | AD38: VALIDA | AE38: 40381 | AJ38: NO DUPLO CHECK, consta a diferença. Porém, a presente certidão cancelou sua anteiror, então crieo que nossa planilha revela o que realmente ocorreu. PARA AVALIAÇÃO GT - incluir no relatório CANCELA A CERTIDÃO FL-012/2009 | AK38: GIULIA/29/05/2025
A39: FL-0319 | B39: 13.769/2004 | D39: 2010-0089023-2 | E39: 40267 | F39: DEFERIDO | G39: YUNY GTIS ATILIO INNOCENTI EMPREENDIMENTOS E PARTICIPACOES LTDA | H39: 09234157/0001-56; | J39: RUA PROFESSOR ATILIO INNOCENTI, 165 E 193 E RUA BELCHIOR SOARES, 40, 50, 56, 64, 68, 78, 187, 197 E 225; | K39: HÉLIO PELEGRINO | L39: ALTERACAO | M39: 299021; | N39: 0135-4; 0133-8; 0064-1; 0066-8; 0067-6; 0068-4; 0069-2; 0071-4; 0072-2; 0070-6; 0065-1; | O39: 3096.86 | P39: NR | T39: 9290.58 | W39: =T39+Q39 -> 9290.58 | X39: CEPAC (título) | Z39: 8672 | AB39: =AA39+Z39 -> 8672 | AC39: FL-012/2009 | AD39: CANCELADA | AE39: 39955 | AJ39: CANCELA A CERTIDÃO FL-018/2008 | CANCELADA PELA CERTIDÃO FL-016/2010 | AK39: GIULIA/29/05/2025
A40: FL-0319 | B40: 13.769/2004 | D40: 2010-0089023-2 | E40: 40267 | F40: DEFERIDO | G40: YUNY GTIS ATILIO INNOCENTI EMPREENDIMENTOS E PARTICIPACOES LTDA | H40: 09234157/0001-56; | J40: RUA PROFESSOR ATILIO INNOCENTI | K40: HÉLIO PELEGRINO | L40: VINCULACAO | M40: 299021; | N40: 0135-4; 0133-8; | O40: 2198.69 | P40: NR | T40: 6596.07 | W40: =T40+Q40 -> 6596.07 | X40: CEPAC (título) | Z40: 6597 | AB40: =AA40+Z40 -> 6597 | AC40: FL-018/2008 | AD40: CANCELADA | AE40: 39770 | AJ40: CANCELADA PELA CERTIDÃO FL-012/2009 | AK40: GIULIA/29/05/2025
A41: FL-0320 | B41: 13.769/2004 | D41: 2008-0013203-0 | E41: 39462 | F41: DEFERIDO | G41: PANAMBY ADMINISTRACAO E PARTICIPACOES LTDA | H41: 00000000/0000-00; | J41: AVENIDA BRIGADEIRO FARIA LIMA, 2.992 | K41: FARIA LIMA | L41: VINCULACAO | M41: 299003; | N41: 0167-4; 0386-3; | O41: 1602 | P41: NR | T41: 52.38 | W41: =T41+Q41 -> 52.38 | X41: CEPAC (título) | Z41: 88 | AB41: =AA41+Z41 -> 88 | AC41: FL-003/2008 | AD41: VALIDA | AE41: 39541 | AK41: GIULIA/27/05/2025
A42: FL-0321 | B42: 13.769/2004 | D42: 2008-0077732-4 | E42: 39518 | F42: DEFERIDO | G42: GAFISA S/A | H42: 01545826/0001-07; | J42: RUAS LEOPOLDO COUTO DE MAGALHAES X LOPES NETO E JUSSEAPE | K42: FARIA LIMA | L42: ALTERACAO | M42: 299016; | N42: 0003-9; 0032-2; 0030-6; 0031-4; 0072-1; 0073-1; 0033-0; 0010-1; 0004-7; 0005-5; 0021-7; 0006-3; 0007-1; 0050-0; 0008-1; 0053-5; 0051-9; 0052-7; | O42: 4920 | P42: R | Q42: 14760 | W42: =T42+Q42 -> 14760 | X42: CEPAC (título) | Z42: 11767 | AB42: =AA42+Z42 -> 11767 | AC42: FL-027/2010 | AD42: VALIDA | AE42: 40500 | AJ42: OLHAR NO PROCESSO - DUPLO CHECK BEM DIVERGENTE DAS CERTIDÕES distribuição de cepac feito pela planilha de duplo check CANCELA A CERTIDÃO FL-005/2008 | AK42: GIULIA/27/05/2025
A43: FL-0321 | B43: 13.769/2004 | D43: 2008-0077732-4 | E43: 39518 | F43: DEFERIDO | G43: GAFISA S/A | H43: 01545826/0001-07; | J43: RUAS LEOPOLDO COUTO DE MAGALHAES X LOPES NETO E JUSSEAPE | K43: FARIA LIMA | L43: VINCULACAO | M43: 299016; | N43: 0003-9; 0032-2; 0030-6; 0031-4; 0072-1; 0073-1; 0033-0; 0010-1; 0004-7; 0005-5; 0021-7; 0006-3; 0007-1; 0050-0; 0008-1; 0053-5; 0051-9; 0052-7; | O43: 4920 | P43: R | Q43: 14760 | W43: =T43+Q43 -> 14760 | X43: CEPAC (título) | Z43: 10597 | AA43: 935 | AB43: =AA43+Z43 -> 11532 | AC43: FL-005/2008 | AD43: CANCELADA | AE43: 40038 | AJ43: distribuição de cepac feito pela planilha de duplo check DADOS OBTIDOS DO APOSTILAMENTO DA CERTIDÃO INICIALMENTE ELABORADA. CANCELADA PELA CERTIDÃO FL-027/2010 | AK43: GIULIA/27/05/2025
A44: FL-0322 | B44: 13.769/2004 | D44: 2008-0179067-7 | E44: 39612 | F44: DEFERIDO | G44: EDIFÍCIO CIDADE JARDIM SPE EMPREENDIMENTO IMOBILIÁRIO L TOA | H44: 09043077/0001-13; | J44: AVENIDA CIDADE JARDIM E RUA MARIO FERRAZ | K44: FARIA LIMA | L44: VINCULACAO | M44: 299004; | N44: 0018-4; 0017-6; 0016-8; 0112-1; 0015-1; | O44: 3396.06 | P44: NR | X44: CEPAC (título) | Z44: 118 | AB44: =AA44+Z44 -> 118 | AC44: FL-002/2009 | AD44: VALIDA | AE44: 39836 | AJ44: ACA NO DUPLO CHECK 8432,13 | AK44: GIULIA/27/05/2025
A45: FL-0322 | B45: 13.769/2004 | D45: 2008-0179067-7 | E45: 39612 | F45: DEFERIDO | G45: EDIFÍCIO CIDADE JARDIM SPE EMPREENDIMENTO IMOBILIÁRIO L TOA | H45: 09043077/0001-13; | J45: AVENIDA CIDADE JARDIM E RUA MARIO FERRAZ | K45: FARIA LIMA | L45: VINCULACAO | M45: 299004; | N45: 0015-1; | O45: 3396.06 | P45: NR | T45: 1756.05 | W45: =T45+Q45 -> 1756.05 | X45: CEPAC (título) | Z45: 2049 | AB45: =AA45+Z45 -> 2049 | AC45: FL-015/2008 | AD45: VALIDA | AE45: 39701 | AJ45: ACA NO DUPLO CHECK 1.756,05 | AK45: GIULIA/27/05/2025
A46: FL-0322 | B46: 13.769/2004 | D46: 2008-0078461-4 | E46: 39519 | F46: DEFERIDO | G46: EDIFICIO CIDADE JARDIM SPE EMPREENDIMENTO IMOBILIARIO LTDA | H46: 09043077/0001-13; | J46: AVENIDA CIDADE JARDIM E RUA MARIO FERRAZ | K46: FARIA LIMA | L46: VINCULACAO | M46: 299004; | N46: 0018-4; 0017-6; 0016-8; 0112-1; | O46: 2810.71 | P46: NR | T46: 8432.13 | W46: =T46+Q46 -> 8432.13 | X46: CEPAC (título) | Z46: 9838 | AB46: =AA46+Z46 -> 9838 | AC46: FL-007/2008 | AD46: VALIDA | AE46: 39553 | AK46: GIULIA/27/05/2025
A47: FL-0323 | B47: 13.769/2004 | D47: 2008-0078866-0 | E47: 39519 | F47: DEFERIDO | G47: JK 16 EMPREENDIMENTO IMOBILIÁRIO S/A; ATINS EMPREENDIMENTOS IMOBILIÁRIOS LTDA | H47: 08977210/0001-46; 04621184/0001-68 | J47: RUA RAMOS BATISTA; RUA IAIÁ GARCIA; AVENIDA JUSCELINO KUBITSCHEK | K47: FARIA LIMA | L47: VINCULACAO | M47: 299022; | N47: 0194-4; 0089-1; 0041-7; 0150-2;0079-4; 0176-6; 0177-4; 0156-1; 0155-3; 0168-5; 0169-3; 0128-6; 0151-0; | O47: 2879.74 | P47: NR | T47: 8639.22 | W47: =T47+Q47 -> 8639.22 | X47: CEPAC (título) | Z47: 14975 | AA47: 1920 | AB47: =AA47+Z47 -> 16895 | AC47: FL-009/2009 | AD47: VALIDA | AE47: 39884 | AJ47: PROPORÇÃO DE CEPACS EXTRAÍDA DO DUPLO CHECK. CONTOU NESTE DOCUMENTO O ANO ERRADO DA CERTIDÃO | AK47: LUCIANA/02/06/2025
A48: FL-0324 | B48: 13.769/2004 | D48: 2008-0118467-0 | E48: 39555 | F48: DEFERIDO | G48: ANTONIO MARZOLA LAUDINO; DYLCEIA STEIN MARZOLA LAUDINO | I48: 288575778-72; 214478588-08 | J48: AVENIDA CARDOSO DE MELO, 1336 | K48: OLIMPÍADAS | L48: ALTERACAO | M48: 299080; | N48: 0080-0; | O48: 2000 | P48: NR | T48: 4000 | W48: =T48+Q48 -> 4000 | X48: CEPAC (título) | Z48: 3334 | AB48: =AA48+Z48 -> 3334 | AC48: FL-014/2008 | AD48: VALIDA | AE48: 39696
A49: FL-0325 | B49: 13.769/2004 | D49: 2008-0118470-0 | E49: 39555 | F49: DEFERIDO | G49: BNI ONIX DESENVOLVIMENTO IMOBILIÁRIO LTDA | H49: 08913617/0001-00; | J49: RUA CASA DO ATOR; RUA ALVORADA; RUA CARMONTELLE | K49: OLIMPÍADAS | L49: ALTERACAO | M49: 299074; | N49: 0022-5; 0023-6; 0024-4; 0026-0; 0028-7; 0018-1; 0091-0; 0092-9; 0075-6; 0074-0; 0095-3; 0096-1; 0032-5; 0025-2; 0027-9; | O49: 2829.97 | P49: NR | T49: 5636.64 | W49: =T49+Q49 -> 5636.64 | X49: CEPAC (título) | Z49: 3754 | AB49: =AA49+Z49 -> 3754 | AC49: FL-012/2008 | AD49: CANCELADA | AE49: 39696 | AK49: LUCIANA/02/06/2025
A50: FL-0325 | B50: 13.769/2004 | D50: 2008-0118470-0 | E50: 39555 | F50: DEFERIDO | G50: BNI ONIX DESENVOLVIMENTO IMOBILIÁRIO LTDA | H50: 08913617/0001-00; | J50: RUA CASA DO ATOR; RUA ALVORADA; RUA CARMONTELLE | K50: OLIMPÍADAS | L50: VINCULACAO | M50: 299074; | N50: 0022-5; 0023-6; 0024-4; 0026-0; 0028-7; 0018-1; 0091-0; 0092-9; 0075-6; 0074-0; 0095-3; 0096-1; 0032-5; 0025-2; 0027-9; | O50: 2822.68 | P50: NR | T50: 5636.64 | W50: =T50+Q50 -> 5636.64 | X50: CEPAC (título) | Z50: 3757 | AB50: =AA50+Z50 -> 3757 | AC50: FL-001/2009 | AD50: CANCELADA | AE50: 39821 | AK50: LUCIANA/02/06/2025
A51: FL-0325 | B51: 13.769/2004 | D51: 2008-0118470-0 | E51: 39555 | F51: DEFERIDO | G51: BNI ONIX DESENVOLVIMENTO IMOBILIÁRIO LTDA | H51: 08913617/0001-00; | J51: RUA CASA DO ATOR; RUA ALVORADA; RUA CARMONTELLE | K51: OLIMPÍADAS | L51: VINCULACAO | M51: 299074; | N51: 0022-5; 0023-6; 0024-4; 0026-0; 0028-7; 0018-1; 0091-0; 0092-9; 0075-6; 0074-0; 0095-3; 0096-1; 0032-5; 0025-2; 0027-9; 0021-1; 0020-1; 0090-2; 0089-9; | O51: 3513 | P51: NR | T51: 5636.64 | W51: =T51+Q51 -> 5636.64 | X51: CEPAC (título) | Z51: 4112 | AB51: =AA51+Z51 -> 4112 | AC51: FL-023/2010 | AD51: VALIDA | AE51: 40478 | AK51: LUCIANA/02/06/2025
A52: FL-0326 | B52: 13.769/2004 | D52: 2008-0174584-1 | E52: 39609 | F52: DEFERIDO | G52: BNI ESMERALDA DESENVOLVIMENTO IMOBILIÁRIO LTDA | H52: 09253260/0001-43; | J52: RUA OLIMPÍADAS, 134 | K52: OLIMPÍADAS | L52: VINCULACAO | M52: 299050; | N52: 0036-2; | O52: 1600 | P52: NR | T52: 2920 | W52: =T52+Q52 -> 2920 | X52: CEPAC (título) | Z52: 3245 | AB52: =AA52+Z52 -> 3245 | AC52: FL-013/2008 | AD52: VALIDA | AE52: 39696 | AK52: LUCIANA/02/06/2025
A53: FL-0328 | B53: 13.769/2004 | D53: 2008-0212890-0 | E53: 39645 | F53: DEFERIDO | G53: LEOPOLDO GREEN EMPREENDIMENTOS E PARTICIPAÇÕES LTDA | H53: 09233161/0001-08; | J53: RUA LEOPOLDO COUTO DE MAGALHÃES JUNIOR; RUA CLODOMIRO AMAZONAS; RUA HORÁCIO LÁFER | K53: HÉLIO PELEGRINO | L53: VINCULACAO | M53: 299018; | N53: 0001-1; 0002-1; 0003-8; 0004-6; 0005-4; 0006-2; 0009-7; 001-7; 001-5; 0042-9; 003-7; 0044-5; 005-8; 0052-6; 0053-4; 0054-2; 0055-0; 0056-9; 0057-7; 0058-5; 0078-1; 0079-8; 0080-1; 0081-1; 0082-1; 0096-8; | O53: 9076.94 | P53: NR | T53: 27230.82 | W53: =T53+Q53 -> 27230.82 | X53: CEPAC (título) | Z53: 23601 | AB53: =AA53+Z53 -> 23601 | AC53: FL-010/2008 | AD53: VALIDA | AE53: 39694 | AK53: LUCIANA/02/06/2025
A54: FL-0329 | B54: 13.769/2004 | D54: 2008-0141637-6 | E54: 39580 | F54: DEFERIDO | G54: GAFISA S/A | H54: 01545826/0001-07; | J54: RUA ARAGUARI, 415 | K54: HÉLIO PELEGRINO | L54: VINCULACAO | M54: 041079; | N54: 0009-6; 0049-5; 0050-9; 0051-7; | O54: 1505.01 | P54: R | Q54: 4515.03 | W54: =T54+Q54 -> 4515.03 | X54: CEPAC (título) | Z54: 3011 | AA54: 1051 | AB54: =AA54+Z54 -> 4062 | AC54: FL-016/2008 | AD54: VALIDA | AE54: 39720 | AJ54: DISTRIBUIÇÃO DE CEPAC EFETUADA CONFORME DESCRITO NO DUPLO CHECK | AK54: LUCIANA/06/06/2025
A55: FL-0331 | B55: 13.769/2004 | D55: 2005-0257352-6 | E55: 38643 | F55: DEFERIDO | G55: VIP INCORPORACOES IMOBILIARIAS LTDA; BANCO OURINVEST S.A., NA QUALIDADE DE INSTITUIÇÃO ADMINISTRADORA DO FUNDO DE INVESTIMENTO IMOBILIARIO PREMIER REALTY | H55: 04950732/0001-01; 78632767/0001-20; | J55: RUA UBERABINHA X RUA QUATA X RUA TEREZA DE CAPUA X AVENIDA HELIO PELLEGRINO | K55: HÉLIO PELEGRINO | L55: VINCULACAO | M55: 299085; | N55: 0065-1; | O55: 5293.34 | P55: NR | T55: 14658.78 | W55: =T55+Q55 -> 14658.78 | X55: CEPAC (título) | Z55: 9773 | AA55: 3260 | AB55: =AA55+Z55 -> 13033 | AC55: FL-016/2009 | AD55: VALIDA | AE55: 40044 | AJ55: DIVISÃO DE CEPACS CONFORME PLANILHA PUBLICADA. | AK55: AMANDA/23/05/2025
A56: FL-0332 | B56: 13.769/2004 | D56: 2007-0176532-8 | E56: 39234 | F56: DEFERIDO | G56: BES EMPREENDIMENTOS E PARTIPACOES S/C LTDA.; | H56: 04572018/0001-19; | J56: RUA DIOGO JACOME, 806 | K56: HÉLIO PELEGRINO | L56: VINCULACAO | M56: 041059; | N56: 0121-4; 0028-5; 0026-9; 0027-7; | O56: 1317.32 | P56: NR | T56: 781.91 | W56: =T56+Q56 -> 781.91 | X56: CEPAC (título) | Z56: 782 | AB56: =AA56+Z56 -> 782 | AC56: FL-007/2009 | AD56: VALIDA | AE56: 39874 | AK56: AMANDA/23/05/2025
A57: FL-0332 | B57: 13.769/2004 | D57: 2017-0030693-2 | E57: 42783 | F57: DEFERIDO | G57: SAL ADMINISTRACAO E INCORPORACAO LTDA.; BES EMPREENDIMENTOS E PARTICIPACOES LTDA.; MHB ADMINISTRACAO E PARCIPACOES LTDA.; | H57: 11731233/0001-80; 04572018/0001-19; 06538651/0001-16; | J57: RUA DIOGO JACOME, 786 | K57: HÉLIO PELEGRINO | L57: ALTERACAO | M57: 041059; | N57: 0120-6; 0121-4; 0027-7; 0026-9; 0028-5; 0033-1; 0122-2; 0024-2; 0032-3; 0025-0; 0002-1; 0068-4; 0069-2; 0070-6; 0071-4; 0072-2; 0073-0; 0074-9; 0075-7; 0076-5; 0077-3; 0078-1; 0079-1; 0080-3; 0081-1; 0066-8; 0017-1; | O57: 7424.21 | P57: NR | T57: 2034.23 | W57: =T57+Q57 -> 2034.23 | X57: CEPAC (título) | Z57: 1143 | AB57: =AA57+Z57 -> 1143 | AC57: FL-004/2017 | AD57: CANCELADA | AE57: 42812 | AJ57: CANCELADA PELA CERTIDÃO FL-007/2017 | AK57: AMANDA/28/05/2025
A58: FL-0332 | B58: 13.769/2004 | D58: 2017-0030693-2 | E58: 42783 | F58: DEFERIDO | G58: SAL ADMINISTRACAO E INCORPORADORA LTDA.; BES EMPREENDIMENTOS E PARTICIPACOES LTDA.; MHB ADMINISTRACAO E PARTICIPACOES LTDA. | H58: 11731233/0001-80; 04572018/0001-19; 06538651/0001-16; | J58: RUA DIOGO JACOME 786 | K58: HÉLIO PELEGRINO | L58: ALTERACAO | M58: 041059; | N58: 0120-6; 0121-4; 0027-7; 0026-9; 0028-5; 0033-1; 0122-2; 0024-2; 0032-3; 0025-0; 0002-1; 0068-4; 0069-2; 0070-6; 0071-4; 0072-2; 0073-0; 0074-9; 0075-7; 0076-5; 0077-3; 0078-1; 0079-1; 0080-3; 0081-1; 0066-8; 0017-1; | O58: 7424.21 | P58: NR | T58: 2034.23 | W58: =T58+Q58 -> 2034.23 | X58: CEPAC (título) | Z58: 1143 | AB58: =AA58+Z58 -> 1143 | AC58: FL-007/2017 | AD58: VALIDA | AE58: 42910 | AJ58: CANCELA A CERTIDÃO FL-004/2017 | AK58: AMANDA/28/05/2025
A59: FL-0333 | B59: 13.769/2004 | D59: 2008-0082363-6 | E59: 39521 | F59: DEFERIDO | G59: LABRADOR INVESTIMENTOS IMOBILIARIOS LTDA.; | H59: 08303517/0001-61; | J59: AVENIDA HELIO PELEGRINO X RUA SILVANIA X RUA DOUTOR ERNANI PEREIRA | K59: HÉLIO PELEGRINO | L59: VINCULACAO | M59: 041076; | N59: 0004-1; 0007-6; 0008-4; 0016-5; 0017-3; 0018-1; 0019-1; 0020-3; 0021-1; 0022-1; 0023-8; 0024-6; 0028-9; 0029-7; 0047-5; 0050-5; | O59: 4429.02 | P59: R | W59: =T59+Q59 -> 0 | X59: CEPAC (título) | AA59: 2953 | AB59: =AA59+Z59 -> 2953 | AC59: FL-019/2008 | AD59: VALIDA | AE59: 39784 | AJ59: COMPLEMENTADA PELA CERTIDÃO FL-017/2009 | AK59: AMANDA/28/05/2025
A60: FL-0333 | B60: 13.769/2004 | D60: 2008-0082363-6 | E60: 39521 | F60: DEFERIDO | G60: LABRADOR INVESTIMENTOS IMOBILIARIOS LTDA.; | H60: 08303517/0001-61; | J60: AVENIDA HELIO PELEGRINO X RUA SILVANIA X RUA DOUTOR ERNANI PEREIRA | K60: HÉLIO PELEGRINO | L60: VINCULACAO | M60: 041076; | N60: 0004-1; 0007-6; 0008-4; 0016-5; 0017-3; 0018-1; 0019-1; 0020-3; 0021-1; 0022-1; 0023-8; 0024-6; 0028-9; 0029-7; 0047-5; 0050-5; | O60: 4429.02 | P60: R | Q60: 13287.05 | W60: =T60+Q60 -> 13287.05 | X60: CEPAC (título) | Z60: 8268 | AB60: =AA60+Z60 -> 8268 | AC60: FL-017/2009 | AD60: VALIDA | AE60: 40064 | AJ60: COMPLEMENTA A CERTIDAO FL-019/2008 | AK60: AMANDA/28/05/2025
A61: FL-0334 | B61: 13.769/2004 | D61: 2007-0396554-5 | E61: 39444 | F61: DEFERIDO | G61: JHS-F INCORPORACOES S/A. | H61: 05345215/0001-68; | J61: AVENIDA HELIO PELEGRINO 480 | K61: HÉLIO PELEGRINO | L61: VINCULACAO | M61: 041283; | N61: 0001-2; 0002-0; 0003-9; 0004-7; 0005-5; 0017-9; 0018-7; 0027-6; 0028-4; 0029-2; 0040-3; 0041-1; 0042-1; 0042-1; 0043-8; 0044-6; 0045-4; 0046-2; 0047-0; 0052-7; 0053-5; 0054-3; | O61: 4619.3 | P61: R | Q61: 13857.9 | W61: =T61+Q61 -> 13857.9 | X61: CEPAC (título) | Z61: 8623 | AA61: 3080 | AB61: =AA61+Z61 -> 11703 | AC61: FL-020/2008 | AD61: VALIDA | AE61: 39794 | AJ61: QUANTIDADE DE CEPACS ALTERADA PELA RETI-RATI (VALOR DIVERGENTE DA PLANILHA PUBLICADA DE ESTOQUE CONSUMIDO) | AK61: AMANDA/28/05/2025
A62: FL-0335 | B62: 13.769/2004 | D62: 2010-0211141-9 | E62: 40393 | F62: DEFERIDO | G62: ESSER GENERAL EMPREENDIMENTOS IMOBILIARIOS LTDA.; | H62: 09083269/0001-53; | J62: RUA CARDEAL ARCOVERDE, 2811 | K62: PINHEIROS | L62: VINCULACAO | M62: 015073; | N62: 0025-5; | O62: 1485 | P62: NR | T62: 1881.9 | W62: =T62+Q62 -> 1881.9 | X62: CEPAC (título) | Z62: 1107 | AB62: =AA62+Z62 -> 1107 | AC62: FL-001/2011 | AD62: VALIDA | AE62: 40547 | AK62: AMANDA/28/05/2025
A63: FL-0336 | B63: 13.769/2004 | D63: 2008-0241666-3 | E63: 39672 | F63: DEFERIDO | G63: REGINA HELENA CHEDE MARIANI; MAGALY DIAS DE SOUZA MARIANI; PAULO SERGIO INNECCO PINTUCCI; MARIA JOSE LANGONE; ESPOLIO DE MARCO FLAVIO INNECCO PINTUCCI; SONIA MARIA VITA PINTUCCI; BRUNO VITA PINTUCCI; BIANCA VITA PINTUCCI; HESA 6 - INVESTIMENTOS IMOBILIARIOS; UPCON DESENVOLVIMENTO IMOBILIARIO LTDA.; | H63: 09343343/0001-23; 08168657/0001-74; | I63: 222355908-53; 042669528-30; 372756408-30; 395374558-15; 372756238-20; 073217238-10; 304572074-17; 041038004-10; | J63: RUA CANARIO, 148 E 160 | K63: HÉLIO PELEGRINO | L63: VINCULACAO | M63: 041038; | N63: 0024-0; 0041-1; | O63: 1080 | P63: R | Q63: 3420 | W63: =T63+Q63 -> 3420 | X63: CEPAC (título) | Z63: 2160 | AA63: 720 | AB63: =AA63+Z63 -> 2880 | AC63: FL-003/2009 | AD63: VALIDA | AE63: 39856 | AJ63: DISTRIBUIÇÃO DE CEPACS RETIRADA DA TABELA PUBLICADA DE ESTOQUE CONSUMIDO | AK63: AMANDA/28/05/2025
A64: FL-0338 | B64: 13.769/2004 | D64: 2009-0100238-7 | E64: 39905 | F64: DEFERIDO | G64: RPB EMPREENDIMENTOS E PARTICIPACOES S/A.; | H64: 08312116/0001-78; | J64: RUA DOUTOR RENATO PAES DE BARROS, 901; RUA PAULA DE OLIVEIRA, 68, 78, 94, 98, 114, 118 | K64: HÉLIO PELEGRINO | L64: VINCULACAO | M64: 016139; | N64: 0100-3; 0035-1; 0036-8; 0037-6; 0038-4; 0039-2; 0040-6; | O64: 1955.04 | P64: R | Q64: 5865.12 | W64: =T64+Q64 -> 5865.12 | X64: CEPAC (título) | Z64: 2347 | AB64: =AA64+Z64 -> 2347 | AC64: FL-011/2009 | AD64: VALIDA | AE64: 39919 | AK64: AMANDA/28/05/2025
A65: FL-0339 | B65: 13.769/2004 | D65: 2008-0254707-5 | E65: 39685 | F65: DEFERIDO | G65: TIGER EVEN EMPREENDIMENTOS IMOBILIARIOS LTDA.; | H65: 08868287/0001-88; | J65: RUA ANNA CAMPOS MELAO; RUA NICOLAU GAGLIARDI; RUA DOUTOR CARLOS ALBERTO DO ESPIRITO SANTO; RUA COSTA CARVALHO | K65: PINHEIROS | L65: VINCULACAO | M65: 083224; | N65: 0001-2; 0002-0; 0003-9; 0004-7; 0005-5; 0006-3; 0007-1; 0008-1; 0009-8; 0010-1; 0011-1; 0012-8; 0013-6; 0014-4; 0015-2; 0016-0; 0017-9; 0018-7; 0019-5; 0020-9; 0021-7; 0022-5; 0023-3; 0024-1; 0025-1; 0026-8; 0027-6; 0028-4; 0029-2; 0030-6; 0031-4; 0032-2; 0033-0; 0034-9; 0035-7; 0036-5; 0037-3; | O65: 3002.51 | P65: R | Q65: 9005.21 | W65: =T65+Q65 -> 9005.21 | X65: CEPAC (título) | Z65: 3002 | AA65: 100 | AB65: =AA65+Z65 -> 3102 | AC65: FL-013/2009 | AD65: VALIDA | AE65: 39983 | AJ65: DISTRIBUIÇÃO DE CEPACS RETIRADA DA TABELA PUBLICADA DE ESTOQUE CONSUMIDO | AK65: AMANDA/28/05/2025
A66: FL-0340 | B66: 13.769/2004 | D66: 2008-0196592-2 | E66: 39630 | F66: DEFERIDO | G66: SEMAITA EMPREENDIMENTOS IMOBILIARIOS LTDA.; | H66: 09099652/0001-08; | J66: RUA CASA DO ATOR, 352, 358, 370, 378, 400, 408 | K66: HÉLIO PELEGRINO | L66: VINCULACAO | M66: 299094; | N66: 0181-7; 0017-9; 0018-7; 0016-0; 0019-5; | O66: 2675 | P66: R | Q66: 8024.6 | W66: =T66+Q66 -> 8024.6 | X66: CEPAC (título) | Z66: 2996 | AB66: =AA66+Z66 -> 2996 | AC66: FL-015/2009 | AD66: VALIDA | AE66: 40044 | AK66: AMANDA/28/05/2025
A67: FL-0341 | B67: 13.769/2004 | D67: 2009-0245317-0 | E67: 40046 | F67: DEFERIDO | G67: YUNY APOLLO EMPREENDIMENTOS LTDA | H67: 10420745/0001-63; | J67: RUA IRLANDINO SANDOVAL , 58, 68 E S/N | K67: FARIA LIMA | L67: VINCULACAO | M67: 083053; | N67: 0098-6; 0099-4; 0158-3; | O67: 1602.36 | P67: R | Q67: 4807.08 | W67: =T67+Q67 -> 4807.08 | X67: CEPAC (título) | Z67: 6009 | AA67: 1470 | AB67: =AA67+Z67 -> 7479 | AC67: FL-015/2011 | AD67: VALIDA | AE67: 40773 | AJ67: DESVINCULAÇÃO DOS 7.479 CEPACS (FL-002/14 DE 1/17/14 ) | AK67: GIULIA/19/05/2025
A68: FL-0342 | B68: 13.769/2004 | D68: 2008-0237638-6 | E68: 39667 | F68: DEFERIDO | G68: ABITAR SPE EMPREENDIMENTOS IMOBILIARIOS S/A , ODEBRECHT S/A, EDUARDO AUGUSTO VIEIRA LEME , YOLANDA LA TORRE FEOLA, DONATA FEOLA FREIRE, JOANNA FEOLA LATORRE | H68: 09397320/0001-00; 05144757/0001-72; | I68: 065692318-04; 014144438-03; 267067267-00; 307724048-36 | J68: RUA LEMOS MONTEIRO, 138, 120, 106, 88, 98, 74, 78, RUA AGOSTINHO CANTÚ, 24, 32, 40, 44, 52, 58, 62, 72, 88, 7 4, 94, 100, 106 E RUA DESEMBAGADOR ARMANDO FAIRBANKS 39, 43, 53, 59, 63, 71, 71-F, 75, 79 E 85 | K68: PINHEIROS | L68: VINCULACAO | M68: 200053; | N68: 0016-7; 0045-0; 0044-2; 0017-5; 0030-2; 0027-2; 0015-9; 0014-0; 0032-8; 0031-0; 0012-4; 0006-1; 0007-8; 0036-1; 0018-3; 0019-1; 0041-8; 0042-6; 0043-4; 0037-1; 0040-1; 0039-6; 0038-8 | O68: 7387.67 | P68: NR | T68: 22163.01 | W68: =T68+Q68 -> 22163.01 | X68: CEPAC (título) | Z68: 11492 | AA68: 4680 | AB68: =AA68+Z68 -> 16172 | AC68: FL-021/2011 | AD68: VALIDA | AE68: 40834 | AK68: GIULIA/19/05/2025
A69: FL-0342 | B69: 13.769/2004 | D69: 2008-0237638-6 | E69: 39667 | F69: DEFERIDO | G69: ABITAR SPE EMPREENDIMENTOS IMOBILIARIOS S/A , ODEBRECHT S/A, EDUARDO AUGUSTO VIEIRA LEME , YOLANDA LA TORRE FEOLA, DONATA FEOLA FREIRE, JOANNA FEOLA LATORRE | H69: 09397320/0001-00; 05144757/0001-72; | I69: 065692318-04; 014144438-03; 267067267-00; 307724048-36 | J69: RUA LEMOS MONTEIRO, 138, 120, 106, 88, 98, 74, 78, RUA AGOSTINHO CANTÚ, 24, 32, 40, 44, 52, 58, 62, 72, 88, 7 4, 94, 100, 106 E RUA DESEMBAGADOR ARMANDO FAIRBANKS 39, 43, 53, 59, 63, 71, 71-F, 75, 79 E 85 | K69: PINHEIROS | L69: VINCULACAO | M69: 200053; | N69: 0016-7; 0045-0; 0044-2; 0017-5; 0030-2; 0027-2; 0015-9; 0014-0; 0032-8; 0031-0; 0012-4; 0006-1; 0007-8; 0036-1; 0018-3; 0019-1; 0041-8; 0042-6; 0043-4; 0037-1; 0040-1; 0039-6; 0038-8 | O69: 7387.67 | P69: NR | T69: 22163.01 | W69: =T69+Q69 -> 22163.01 | X69: CEPAC (título) | Z69: 11492 | AA69: 4680 | AB69: =AA69+Z69 -> 16172 | AC69: FL-018/2011 | AD69: CANCELADA | AE69: 40786 | AJ69: diz que esta cancelada , mas no processo "valido" ela nao aparece como tendo sido substituida | AK69: GIULIA/19/05/2025
A70: FL-0342 | B70: 13.769/2004 | D70: 2008-0237638-6 | E70: 39667 | F70: DEFERIDO | G70: ABITAR SPE EMPREENDIMENTOS IMOBILIARIOS S/A | H70: 09397320/0001-00; | J70: RUA LEMOS MONTEIRO, 138, 120, 106, 88, 98, 74, 78, RUA AGOSTINHO CANTÚ, 24, 32, 40, 44, 52, 58, 62, 72 E RUA DESEMBAGADOR ARMANDO FAIRBANKS 39, 43, 53, 59, 63, 71, | K70: PINHEIROS | L70: VINCULACAO | M70: 200053; | N70: 0016-7; 0045-0; 0044-2; 0017-5; 0030-2; 0027-2; 0015-9; 0014-0; 0032-8; 0031-0; 0012-4; 0006-1; 0007-8; 0036-1; 0018-3; 0019-1; | O70: 6449.25 | P70: NR | T70: 19347.75 | W70: =T70+Q70 -> 19347.75 | X70: CEPAC (título) | Z70: 13258 | AB70: =AA70+Z70 -> 13258 | AC70: FL-018/2010 | AD70: CANCELADA | AE70: 40779 | AK70: GIULIA/19/05/2025
A71: FL-0342 | B71: 13.769/2004 | D71: 2008-0237638-6 | E71: 39667 | F71: DEFERIDO | G71: ABITAR SPE EMPREENDIMENTOS IMOBILIARIOS S/A | H71: 09397320/0001-00; | J71: RUA LEMOS MONTEIRO, 138, 120, 106, 88, 98, 74, 78, RUA AGOSTINHO CANTÚ, 24, 32, E RUA DESEMBAGADOR ARMANDO FAIRBANKS 39, 43, 53, | K71: PINHEIROS | L71: VINCULACAO | M71: 200053; | N71: 0016-7; 0045-0; 0044-2; 0017-5; 0030-2; 0027-2; 0015-9; 0014-0; 0032-8; 0031-0; 0012-4; 0006-1; 0007-8; 0036-1; 0018-3; 0019-1; | O71: 3421.76 | P71: NR | T71: 19347.75 | W71: 2372.04 | X71: CEPAC (título) | Z71: 2649 | AB71: =AA71+Z71 -> 2649 | AC71: FL-018/2009 | AD71: CANCELADA | AE71: 40779 | AK71: GIULIA/19/05/2025
A72: FL-0343 | B72: 13.769/2004 | D72: 2008-0247707-7 | E72: 39678 | F72: DEFERIDO | G72: MPH EMPREENDIMENTO IMOBILIÁRIO LTDA, HELFER COMÉRCIO E PARTICIPAÇÕES LTDA, | H72: 08486298/0001-01; 64907868/0001-52 | J72: RUA OLIMPÍADAS 360 E RUA FIDÊNCIO RAMOS 257 | K72: OLIMPÍADAS | L72: VINCULACAO | N72: 0083-4; 0065-6; 0039-7; | O72: 928 | P72: NR | W72: =T72+Q72 -> 0 | X72: CEPAC (título) | AA72: 147 | AB72: =AA72+Z72 -> 147 | AC72: FL-019/2009 | AD72: VALIDA | AE72: 40086 | AJ72: PROPOSTA ADERIU SOMENTE PARA QUEBRA DE T.O. EM UMA PARTE DO TERRENO - INCIDENTE SOMENTE SOBRE O LOTE 0083 | AK72: GIULIA/19/05/2025
A73: FL-0344 | B73: 13.769/2004 | D73: 2009-0075811-9 | E73: 39883 | F73: DEFERIDO | G73: VITACON EMPREENDIMENTOS LTDA | H73: 09361394/0001-88; | J73: RUA DOUTOR CARDOSO DE MELO, 6226/630 E RUA GOMES DE CARVALHO | K73: HÉLIO PELEGRINO | L73: VINCULACAO | M73: 299101; | N73: 0093-0; | O73: 2499 | P73: MISTO | Q73: 4662 | T73: 2835 | W73: =T73+Q73 -> 7497 | X73: CEPAC (título) | Z73: 3755 | AB73: =AA73+Z73 -> 3755 | AC73: FL-011/2010 | AD73: VALIDA | AE73: 40302 | AJ73: COMPLEMENTA A CERTIDÃO FL-020/2009 | AK73: GIULIA/19/05/2025
A74: FL-0344 | B74: 13.769/2004 | D74: 2009-0075811-9 | E74: 39883 | F74: DEFERIDO | G74: VITACON EMPREENDIMENTOS LTDA | H74: 09361394/0001-88; | J74: RUA DOUTOR CARDOSO DE MELO, 6226/630 E RUA GOMES DE CARVALHO | K74: HÉLIO PELEGRINO | L74: VINCULACAO | M74: 299101; | N74: 0093-0; | O74: 2499 | P74: MISTO | X74: CEPAC (título) | AA74: 254 | AB74: =AA74+Z74 -> 254 | AC74: FL-020/2009 | AD74: VALIDA | AE74: 40114 | AK74: GIULIA/19/05/2025
A75: FL-0345 | B75: 13.769/2004 | D75: 2009-0316661-1 | E75: 40115 | F75: DEFERIDO | G75: ZAMORA INCORPORAÇÃO LTDA | H75: 08628993/0001-52; | J75: RUA GILBERTO SABINO, 171 , 177, 187, 197, 199, 207, 215, 221 RUA CAPRI, 60, 66, 68, 88 | K75: PINHEIROS | L75: VINCULACAO | M75: 083100; | N75: 0080-4; 0077-4; 0076-6; 0025-1; 0027-8; 0028-6; 0029-4; 0075-8; 0018-9 | O75: 3719.7 | P75: NR | T75: 11137.89 | W75: =T75+Q75 -> 11137.89 | X75: CEPAC (título) | Z75: 5775 | AB75: =AA75+Z75 -> 5775 | AC75: FL-021/2010 | AD75: VALIDA | AE75: 40461 | AK75: GIULIA/19/05/2025
A76: FL-0345 | B76: 13.769/2004 | D76: 2009-0316661-1 | E76: 40115 | F76: DEFERIDO | G76: ZAMORA INCORPORAÇÃO LTDA | H76: 08628993/0001-52; | J76: RUA GILBERTO SABINO, 171 , 177, 187, 197, 199, 207, 215, 221 RUA CAPRI, 60, 66, 68, 88 | K76: PINHEIROS | L76: VINCULACAO | M76: 083100; | N76: 0080-4; 0077-4; 0076-6; 0025-1; 0027-8; 0028-6; 0029-4; 0075-8; 0018-9 | O76: 3719.7 | P76: NR | T76: 11002.87 | W76: =T76+Q76 -> 11002.87 | X76: CEPAC (título) | Z76: 5700 | AB76: =AA76+Z76 -> 5700 | AC76: FL-001/2010 | AD76: CANCELADA | AE76: 40182 | AK76: GIULIA/19/05/2025
A77: FL-0346 | B77: 13.769/2004 | D77: 2009-0214443-6 | E77: 40021 | F77: DEFERIDO | G77: MAX CASA EMPREENDIMENTOS IMOBILIARIOSLTDA. | H77: 10212829/0001-01; | J77: RUA RUA FIANDEIRAS, 326 E RUA CLODOMIRO AMAZONAS, 1.378, 1.382, 1.384 E 1.386 | K77: HÉLIO PELEGRINO | L77: VINCULACAO | M77: 299066; | N77: 0116-5; 0058-4; | O77: 2385.83 | P77: MISTO | Q77: 1706.31 | T77: 26.47 | W77: =T77+Q77 -> 1732.78 | X77: CEPAC (título) | Z77: 710 | AB77: =AA77+Z77 -> 710 | AC77: FL-007/2011 | AD77: VALIDA | AE77: 40626 | AK77: GIULIA/19/05/2025
A78: FL-0347 | B78: 13.769/2004 | D78: 2009-0296830-7 | E78: 40094 | F78: DEFERIDO | G78: IUNI PARTICIPAÇÕES E SERVIÇOS S/A | H78: 08508931/0001-07; | J78: RUA CARDEAL ARCOVERDE E PEDRO CRISTI | K78: PINHEIROS | L78: VINCULACAO | M78: 015055; | N78: 0005-2; 0006-0; 0007-9; 0008-7; 0040-0; 0041-9; 0042-7; 0043-5; 0044-3; | O78: 1403.56 | P78: NR | T78: 4210.68 | W78: =T78+Q78 -> 4210.68 | X78: CEPAC (título) | Z78: 2374 | AA78: 26 | AB78: =AA78+Z78 -> 2400 | AC78: FL-022/2009 | AD78: VALIDA | AE78: 40788 | AJ78: CONFERIR CERTIDÃO 022/2009 - INLCUIR DADOS, POIS ESTA CERTIDÃO SE TRATA DE RETI-RATI | AK78: GIULIA/19/05/2025
A79: FL-0348 | B79: 13.769/2004 | D79: 2009-0208614-2 | E79: 40011 | F79: DEFERIDO | G79: SP LAPIN EMPREENDIMENTOS IMOBILIARIOS LTDA. | H79: 09026078/0001-50; | J79: RUA BENEDITO LAPIN, 161 | K79: HÉLIO PELEGRINO | L79: VINCULACAO | M79: 016167; | N79: 0039-4; 0065-3; 0066-1; 0067-1; 0068-6; 0092-0; | O79: 1274.78 | P79: R | Q79: 3824.34 | W79: =T79+Q79 -> 3824.34 | X79: CEPAC (título) | Z79: 1530 | AB79: =AA79+Z79 -> 1530 | AC79: FL-009/2010 | AD79: VALIDA | AE79: 40261 | AK79: GIULIA/19/05/2025
A80: FL-0349 | B80: 13.769/2004 | D80: 2009-0327976-9 | E80: 40127 | F80: DEFERIDO | G80: F. REIS ADMINISTRACAO DE IMOVEIS LTDA | H80: 00076468/0001-60; | J80: RUA DOUTOR ALCEU DE CAMPOS RODRIGUES 126, RUA GUILHERME BANNITZ 201 E RUA DOUTOR JOAO CLIMACO PEREIRA 88 | K80: HÉLIO PELEGRINO | L80: VINCULACAO | M80: 016146; | N80: 0059-7; 0039-2; 0065-1 | O80: 2091.54 | P80: NR | T80: 4183.08 | W80: =T80+Q80 -> 4183.08 | X80: CEPAC (título) | Z80: 4184 | AB80: =AA80+Z80 -> 4184 | AC80: FL-007/2010 | AD80: VALIDA | AE80: 40248 | AK80: GIULIA/19/05/2025
A81: FL-0350 | B81: 13.769/2004 | D81: 2009-0353717-2 | E81: 40150 | F81: DEFERIDO | G81: LEGACY EMPREENDIMENTOS IMOBILIARIOS LTDA | H81: 08691907/0001-56; | J81: RUA PAES LEME, 136 | K81: PINHEIROS | L81: VINCULACAO | M81: 083212; | N81: 0115-6; | O81: 1561.7 | P81: NR | T81: 3123.4 | W81: =T81+Q81 -> 3123.4 | X81: CEPAC (título) | Z81: 1736 | AB81: =AA81+Z81 -> 1736 | AC81: FL-003/2010 | AD81: VALIDA | AE81: 40185 | AK81: GIULIA/19/05/2025
A82: FL-0351 | B82: 13.769/2004 | D82: 2009-0354976-6 | E82: 40151 | F82: DEFERIDO | G82: JOÃO SALLES FERREIRA ALVES; GISELDA BITTENCOURT FERREIRA ALVES; DIALOGO ENGENHARIA E CONSTRUÇÃO LTDA; OCNCIVIL CONSTRUTORA E INCORPORADORA LTDA; LUCIUS EMPREENDIMENTOS IMOBILIÁRIOS LTDA; | H82: 57132417/0001-25; 72951130/0001-10; 46213765/0001-10; | I82: 023483578-87; 149018338-80; | J82: RUA SÃO TOMÉ Nº 73 | K82: OLIMPÍADAS | L82: VINCULACAO | M82: 299039; | N82: 0068-4; | O82: 1455 | P82: R | Q82: 2910 | W82: =T82+Q82 -> 2910 | X82: CEPAC (título) | Z82: 1455 | AB82: =AA82+Z82 -> 1455 | AC82: FL-004/2010 | AD82: VALIDA | AE82: 40235 | AK82: VITOR/19/05/2025
A83: FL-0352 | B83: 13.769/2004 | D83: 2009-0370036-7 | E83: 40168 | F83: DEFERIDO | G83: BERNE EMPREENDIMENTOS IMOBILIÁRIOS LTDA | H83: 09257400/0001-51; | J83: RUA LEOPOLDO COUTO DE MAGALHÃES JÚNIOR | K83: HÉLIO PELEGRINO | L83: VINCULACAO | M83: 016134; | N83: 0002-0; 0032-0; 0001-2; 0031-4; 0030-6; 0029-2; 0017-9 | O83: 1293 | P83: R | Q83: 3879 | W83: =T83+Q83 -> 3879 | X83: CEPAC (título) | Z83: 1552 | AB83: =AA83+Z83 -> 1552 | AC83: FL-006/2010 | AD83: VALIDA | AE83: 40240 | AK83: VITOR/19/05/2025
A84: FL-0353 | B84: 13.769/2004 | D84: 2008-0320243-8 | E84: 40240 | F84: DEFERIDO | G84: GREEN DESENVOLVIMENTO IMOBILIÁRIO LTDA | H84: 09253140/0001-46; | J84: RUA GOMES DE CARVALHO Nº 850, 862 E 872 | K84: OLIMPÍADAS | L84: VINCULACAO | M84: 299082; | N84: 0007-9; 0074-5; 0075-3; | O84: 1500 | P84: R | Q84: 3000 | W84: =T84+Q84 -> 3000 | X84: CEPAC (título) | Z84: 1500 | AB84: =AA84+Z84 -> 1500 | AC84: FL-005/2010 | AD84: VALIDA | AE84: 40240 | AK84: VITOR/19/05/2025
A85: FL-0354 | B85: 13.769/2004 | D85: 2010-0025284-8 | E85: 40311 | F85: DEFERIDO | G85: EUGÊNIO DE MEDEIROS EMPREENDIMENTO IMOBILIÁRIO SPE S/A | H85: 08856152/0001-00; | J85: RUA EUGÊNIO DE MEDEIROS Nº 303, 287, S/N, 263, 243, 235 | K85: PINHEIROS | L85: VINCULACAO | M85: 083103; | N85: 0009-3; 0010-7; 0011-5; 0012-3; 0049-2; 0091-3; | O85: 5510.48 | P85: NR | T85: 16530.36 | W85: =T85+Q85 -> 16530.36 | X85: CEPAC (título) | Z85: 9076 | AB85: =AA85+Z85 -> 9076 | AC85: FL-013/2010 | AD85: VALIDA | AE85: 40311 | AJ85: ACA ESTÁ REGISTRADO NO CAMPO 'ACA R', PORÉM É 'ACA NR' | AK85: VITOR/19/05/2025
A86: FL-0356 | B86: 13.769/2004 | D86: 2009-0286284-3 | E86: 40668 | F86: DEFERIDO | G86: BOLSA DE IMÓVEIS DESENVOLVIMENTO IMOBILIÁRIO LTDA | H86: 04913697/0001-42; | J86: RUA DOUTOR MÁRIO FERRAZ X RUA ADOLFO TABACOW X RUA ARAÇARI | K86: FARIA LIMA | L86: VINCULACAO | M86: 299002; | N86: 0073-8; 0072-1; 0071-1; 0070-3; 0089-4; 0017-7; 0016-9 | O86: 1283.11 | P86: R | Q86: 3848.89 | W86: =T86+Q86 -> 3848.89 | X86: CEPAC (título) | Z86: 2961 | AB86: =AA86+Z86 -> 2961 | AC86: FL-009/2011 | AD86: VALIDA | AE86: 40668 | AK86: VITOR/19/05/2025
A87: FL-0357 | B87: 13.769/2004 | D87: 2009-0226480-6 | E87: 40030 | F87: DEFERIDO | G87: EXTO HUMAITÁ EMPREENDIMENTOS IMOBILIÁRIOS SPE LTDA; CONSTRUTORA HUMAITÁ S/A | H87: 10829878/0001-98; 60675014/0001-37; | J87: RUA ALVORADA Nº 109, 212, S/Nº E 153 | K87: HÉLIO PELEGRINO | L87: VINCULACAO | M87: 299177; | N87: 0590-9; 0051-6; | O87: 2850 | P87: R | Q87: 8548.005 | W87: =T87+Q87 -> 8548.005 | X87: CEPAC (título) | Z87: 3192 | AB87: =AA87+Z87 -> 3192 | AC87: FL-012/2010 | AD87: VALIDA | AE87: 40302 | AK87: VITOR/19/05/2025
A88: FL-0359 | B88: 13.769/2004 | D88: 2010-0140132-4 | E88: 40317 | F88: DEFERIDO | G88: TS-4 FLT DESENVOLVIMENTO IMOBILIÁRIO LTDA | H88: 08074339/0001-44; | J88: AVENIDA BRIGADEIRO FARIA LIMA, AVENIDA HORÁCIO LAFER E RUA LOPES NETO | K88: FARIA LIMA | L88: VINCULACAO | M88: 299011; | N88: 0024-9; 0028-1; 0029-1; 0030-3; 0031-1; 0033-8; 0034-6; 0037-0; 0038-9; 0039-7; 0040-0; 0041-9; 0076-1; 0077-1; 0082-6; 0083-4; 0085-0; 0099-0; 0100-8; 0101-6; 0102-6; 0103-2; 0122-9; 0127-1; 0185-7; 0188-1; 0189-1; 0223-3; 0224-1; 0225-1; 0226-8; | O88: 10318.87 | P88: NR | T88: 7189.1582 | W88: =T88+Q88 -> 7189.1582 | X88: CEPAC (título) | Z88: 5103 | AB88: =AA88+Z88 -> 5103 | AC88: FL-015/2010 | AD88: VALIDA | AE88: 40331 | AK88: VITOR/19/05/2025
A89: FL-0360 | B89: 13.769/2004 | D89: 2010-0157728-7 | E89: 40336 | F89: DEFERIDO | G89: YUNY HALLEY EMPREENDIMENTOS S.A; WALTER FRANCISCO DE ABREU; MAIRA MILENA NEVES DE OLIVEIRA ABREU; JOSÉ FRANCISCO DE ABREU JÚNIOR; SILVIA MANCIO DE CAMARGO ABREU; | H89: 10420716/0001-56; | I89: 029206518-38; 194703928-94; 895624968-72; 245609338-41; | J89: RUA CARDEAL ARCOVERDE Nº 2450, 2464, 2468, 2474 E 2478 E RUA BALTAZAR CARRASCO Nº 181 | K89: PINHEIROS | L89: VINCULACAO | M89: 083035; | N89: 0050-3; 0023-6; 0012-0; 0013-9; | O89: 1249.91 | P89: NR | T89: 3749.73 | W89: =T89+Q89 -> 3749.73 | X89: CEPAC (título) | Z89: 2084 | AB89: =AA89+Z89 -> 2084 | AC89: FL-005/2011 | AD89: CANCELADA | AE89: 40616 | AK89: VITOR/29/05/2025
A90: FL-0360 | B90: 13.769/2004 | D90: 2010-0157728-7 | E90: 40336 | F90: DEFERIDO | G90: YUNY HALLEY EMPREENDIMENTOS S.A; WALTER FRANCISCO DE ABREU; MAIRA MILENA NEVES DE OLIVEIRA ABREU; JOSÉ FRANCISCO DE ABREU JÚNIOR; SILVIA MANCIO DE CAMARGO ABREU; | H90: 10420716/0001-56; | I90: 029206518-38; 194703928-94; 895624968-72; 245609338-41; | J90: RUA CARDEAL ARCOVERDE Nº 2450, 2464, 2468, 2474 E 2478 E RUA BALTAZAR CARRASCO Nº 181 | K90: PINHEIROS | L90: ALTERACAO | M90: 083035; | N90: 0050-3; 0023-6; 0012-0; 0013-9; 0053-8; 0054-6; 0055-4; 0056-2; 0057-0; 0058-9; 0059-7; 0060-0; | O90: 1644.53 | P90: NR | T90: 4933.59 | W90: =T90+Q90 -> 4933.59 | X90: CEPAC (título) | Z90: 2741 | AB90: =AA90+Z90 -> 2741 | AC90: FL-013/2011 | AD90: CANCELADA | AE90: 40721 | AJ90: SUBSTITUI CERTIDÃO FL-005/2011, QUE FICA CANCELADA. REQUERIMENTO CLASSIFICADO COMO VINCULAÇÃO | AK90: VITOR/29/05/2025
A91: FL-0360 | B91: 13.769/2004 | D91: 2010-0157728-7 | E91: 40336 | F91: DEFERIDO | G91: YUNY HALLEY EMPREENDIMENTOS S.A; WALTER FRANCISCO DE ABREU; MAIRA MILENA NEVES DE OLIVEIRA ABREU; JOSÉ FRANCISCO DE ABREU JÚNIOR; SILVIA MANCIO DE CAMARGO ABREU; | H91: 10420716/0001-56; | I91: 029206518-38; 194703928-94; 895624968-72; 245609338-41; | J91: RUA CARDEAL ARCOVERDE Nº 2450, 2464, 2468, 2474 E 2478 E RUA BALTAZAR CARRASCO Nº 181 | K91: PINHEIROS | L91: ALTERACAO | M91: 083035; | N91: 0050-3; 0023-6; 0012-0; 0013-9; 0053-8; 0054-6; 0055-4; 0056-2; 0057-0; 0058-9; 0059-7; 0060-0; | O91: 1644.53 | P91: NR | T91: 4933.59 | W91: =T91+Q91 -> 4933.59 | X91: CEPAC (título) | Z91: 2741 | AB91: =AA91+Z91 -> 2741 | AC91: FL-023/2011 | AD91: VALIDA | AE91: 40834 | AJ91: SUBSTITUI CERTIDÃO FL-013/2011, QUE FICA CANCELADA.REQUERIMENTO CLASSIFICADO COMO VINCULAÇÃO | AK91: VITOR/29/05/2025
A92: FL-0361 | B92: 13.769/2004 | D92: 2010-0150597-9 | E92: 40326 | F92: DEFERIDO | G92: TEOEMP EMPREENDIMENTOS IMOBILIÁRIOS SPE LTDA; ESPÓLIO DE MARIANGELA IASI FRACCAROLI; IRAHY GOLDSCHMIDT; ITOBY GOLDSCHMIDT; MAJOY GOLDSCHMIDT ABBONDANZA; JURANDYR ÍNDIO DO BRASIL GOLDSCHMIDT; MARIA THEREZA CALDEIRA LEITE; GERALDO SIDNEY LEITE; JOÃO BATISTA CALDEIRA (DESAPARECIDO); ESPÓLIO DE SERAFIM DOS ANJOS CALDEIRA; ESPÓLIO DE ANA DO CÉU CALDEIRA; ESPÓLIO DE TEREZA DE JESUS CALDEIRA; ESPOLIO DE MARCELINA CALDEIRA MORENO; LUCIA MARTORELLI SALLES; ANTONIO CARLOS SALLES; ROSEL Y SALLES LIMA; JOSÉ HENRIQUE SALLES; MARIA VICENTINA GALLETA SALLES; SYLVIO FERNANDO SALLES; MÁRCIA REGINA SALLES; JOSÉ BASILE; MARIA DO CARMO BASILE; MARISA APARECIDA BASILE PACE; | H92: 11511845/0001-68; | I92: 029109048-65; 608836008-97; 391838748-87; 175297558-89; 020700738-15; 095409978-87; 037905338-15; 220632428-87; 657210398-68; 676849208-04; 064523658-60; 287580858-31; 287580858-31; 125215218-40; 205339358-06; 114914698-20; 165811968-19; 945820098-91; | J92: RUA DOS PINHEIROS, 1629, 1631, 1637, 1641, 1647, 1651, 1657, 1659, 1663, 1667, 1669, 1673 E 1677, RUA CLAUDIO SOARES, 48, 50 E 56 | K92: PINHEIROS | L92: ALTERACAO | M92: 015073; | N92: 0102-2; 0106-5; 0107-3; 0108-1; 0112-1;.0002-6; 0003-4; 0104-9; 0105-7; 0075-1; 0074-3; 0073-5; | O92: 3104.52 | P92: NR | T92: 6459.04 | W92: =T92+Q92 -> 6459.04 | X92: CEPAC (título) | Z92: 3435 | AB92: =AA92+Z92 -> 3435 | AC92: FL-022/2011 | AD92: VALIDA | AE92: 40834 | AJ92: O ARQUIVO DO DUPLO CHECK NAO CONFERE COM AS INFORMAÇOES DAS CERTIDOES ( CONSTA ACA NR 750, E 412 DE CEPAC) - ENTENDO QUE DEVEMOS MANTER COMO ESTÁ NA PLANILHA - AVALIAR COM GT CANCELA A CERTIDÃO FL-017/2010 | AK92: GIULIA/27/05/2025
A93: FL-0361 | B93: 13.769/2004 | D93: 2010-0150597-9 | E93: 40326 | F93: DEFERIDO | G93: TEOEMP EMPREENDIMENTOS IMOBILIÁRIOS SPE LTDA; ESPÓLIO DE MARIANGELA IASI FRACCAROLI; IRAHY GOLDSCHMIDT; ITOBY GOLDSCHMIDT; MAJOY GOLDSCHMIDT ABBONDANZA; JURANDYR ÍNDIO DO BRASIL GOLDSCHMIDT; MARIA THEREZA CALDEIRA LEITE; GERALDO SIDNEY LEITE; JOÃO BATISTA CALDEIRA (DESAPARECIDO); ESPÓLIO DE SERAFIM DOS ANJOS CALDEIRA; ESPÓLIO DE ANA DO CÉU CALDEIRA; ESPÓLIO DE TEREZA DE JESUS CALDEIRA; ESPOLIO DE MARCELINA CALDEIRA MORENO; LUCIA MARTORELLI SALLES; ANTONIO CARLOS SALLES; ROSEL Y SALLES LIMA; JOSÉ HENRIQUE SALLES; MARIA VICENTINA GALLETA SALLES; SYLVIO FERNANDO SALLES; MÁRCIA REGINA SALLES; JOSÉ BASILE; MARIA DO CARMO BASILE; MARISA APARECIDA BASILE PACE; | H93: 11511845/0001-68; | I93: 029109048-65; 608836008-97; 391838748-87; 175297558-89; 020700738-15; 095409978-87; 037905338-15; 220632428-87; 657210398-68; 676849208-04; 064523658-60; 287580858-31; 287580858-31; 125215218-40; 205339358-06; 114914698-20; 165811968-19; 945820098-91; | J93: RUA DOS PINHEIROS, 1629, 1631, 1637, 1641, 1647, 1651, 1657, 1659, 1663, 1667, 1669, 1673 E 1677, RUA CLAUDIO SOARES, 48, 50 E 56 | K93: PINHEIROS | L93: ALTERACAO | M93: 015073; | N93: 0102-2; 0106-5; 0107-3; 0108-1; 0112-1;.0002-6; 0003-4; 0104-9; 0105-7; 0075-1; 0074-3; 0073-5; | O93: 3104.52 | P93: NR | T93: 6459.04 | W93: =T93+Q93 -> 6459.04 | X93: CEPAC (título) | Z93: 3435 | AB93: =AA93+Z93 -> 3435 | AC93: FL-019/2011 | AD93: CANCELADA | AE93: 40788 | AJ93: CANCELA A CERTIDÃO FL-017/2010 | CANCELADA PELA CERTIDÃO FL-022/2011 (OBS: NÃO LOCALIZADA NO DUPLO CHECK) | AK93: GIULIA/27/05/2025
A94: FL-0361 | B94: 13.769/2004 | D94: 2010-0150597-9 | E94: 40326 | F94: DEFERIDO | G94: TEOEMP EMPREENDIMENTOS IMOBILIÁRIOS SPE LTDA; ESPÓLIO DE MARIANGELA IASI FRACCAROLI; representado por sua Inventariante TEREZA FRACCAROLI OZORES; IRAHY GOLDSCHMIDT; ITOBY GOLDSCHMIDT; MAJOY GOLDSCHMIDT ABBONDANZA; JURANDYR ÍNDIO DO BRASIL GOLDSCHMIDT | H94: 11511845/0001-68; | I94: 029109048-65; 199324768-89; 608836008-97; 391838748-87; 175297558-89; 020700738-15; | J94: RUA DOS PINHEIROS, 1629, 1631, 1637, 1641, 1647, 1651, 1657, 1659, 1663, 1667, 1669, 1673 E 1677, RUA CLAUDIO SOARES, 48, 50 | K94: PINHEIROS | L94: VINCULACAO | M94: 015073; | N94: 0102-2; 0106-5; 0107-3; 0108-1; 0112-1;.0002-6; 0003-4; 0104-9; 0105-7; 0075-1; 0074-3; | O94: 2854.52 | P94: NR | T94: 5709.04 | W94: =T94+Q94 -> 5709.04 | X94: CEPAC (título) | Z94: 3023 | AB94: =AA94+Z94 -> 3023 | AC94: FL-017/2010 | AD94: CANCELADA | AE94: 40788 | AJ94: CANCELADA PELA CERTIDÃO FL-019/2011 | AK94: GIULIA/27/05/2025
A95: FL-0362 | B95: 13.769/2004 | D95: 2010-0171731-3 | E95: 40350 | F95: DEFERIDO | G95: COMPANHIA BRASILEIRA DE DISTRIBUICAO | H95: 47508411/0001-56; | J95: RUAS AMARO CAVALHEIRO, RUA PAES LEME E RUA BUTANTA | K95: PINHEIROS | L95: ALTERACAO | M95: 083220; | N95: 0173-8; | O95: 17211.78 | P95: MISTO | Q95: 13144 | T95: 8467.07 | W95: =T95+Q95 -> 21611.07 | X95: CEPAC (título) | Z95: 10037 | AB95: =AA95+Z95 -> 10037 | AC95: FL-024/2011 | AD95: VALIDA | AE95: 40834 | AJ95: NAO CONSTA NA CERTDIDÃO O CANCELAMENTO DA NUMERO FL- 012/2011 | AK95: GIULIA/27/05/2025
A96: FL-0362 | B96: 13.769/2004 | D96: 2010-0171731-3 | E96: 40350 | F96: DEFERIDO | G96: COMPANHIA BRASILEIRA DE DISTRIBUICAO | H96: 47508411/0001-56; | J96: RUAS AMARO CAVALHEIRO, RUA PAES LEME E RUA BUTANTA | K96: PINHEIROS | L96: VINCULACAO | M96: 083220; | N96: 0173-8; | O96: 17211.78 | P96: MISTO | Q96: 13144 | T96: 8467.07 | W96: =T96+Q96 -> 21611.07 | X96: CEPAC (título) | Z96: 10037 | AB96: =AA96+Z96 -> 10037 | AC96: FL-012/2011 | AD96: CANCELADA | AE96: 40710 | AJ96: CANCELADA PELA CERTIDÃO FL-024/2011 | AK96: GIULIA/27/05/2025
A97: FL-0363 | B97: 13.769/2004 | D97: 2014-0162712-5 | E97: 41800 | F97: DEFERIDO | G97: ROBERTO ELIAS CURY; LUIZ ROBERTO DE AZEVEDO SOARES CURY; | I97: 008537048-72; 065417648-59; | J97: RUA HORÁCIO LAFER E NAPOLEÃO MICHEL | K97: FARIA LIMA | L97: ALTERACAO | M97: 299012; | N97: 0125-8; | O97: 2513.72 | P97: R | W97: =T97+Q97 -> 0 | X97: CEPAC (título) | AA97: 347 | AB97: =AA97+Z97 -> 347 | AC97: FL-008/2014 | AD97: VALIDA | AE97: 41876 | AK97: GIULIA/27/05/2025
A98: FL-0363 | B98: 13.769/2004 | D98: 2014-0162712-5 | E98: 41800 | F98: DEFERIDO | G98: ROBERTO ELIAS CURY; | I98: 008537048-72; | J98: RUA HORACIO LAFER E RUA NAPOLEAO MICHEL | K98: FARIA LIMA | L98: ALTERACAO | M98: 299012; | N98: 0125-8; | O98: 2513.72 | P98: R | Q98: 543.29 | W98: =T98+Q98 -> 543.29 | X98: CEPAC (título) | Z98: 32 | AB98: =AA98+Z98 -> 32 | AC98: FL-004/2013 | AD98: VALIDA | AE98: 41354 | AK98: GIULIA/27/05/2025
A99: FL-0363 | B99: 13.769/2004 | D99: 2014-0162712-5 | E99: 41800 | F99: DEFERIDO | G99: ROBERTO ELIAS CURY; | I99: 008537048-72; | J99: RUA HORACIO LAFER E RUA NAPOLEAO MICHEL | K99: FARIA LIMA | L99: VINCULACAO | M99: 299012; | N99: 0125-8; | O99: 2499.01 | P99: R | Q99: 6997.9 | W99: =T99+Q99 -> 6997.9 | X99: CEPAC (título) | Z99: 5383 | AB99: =AA99+Z99 -> 5383 | AC99: FL-008/2011 | AD99: VALIDA | AE99: 40658 | AK99: GIULIA/27/05/2025
A100: FL-0364 | B100: 13.769/2004 | D100: 2008-0188232-6 | E100: 39622 | F100: DEFERIDO | G100: FERREIRA DE ARAUJO EMPREENDIMENTO IMOBILIARIO SPE LTDA; | H100: 09326746/0001-64; | J100: RUA FERREIRA DE ARAUJO, 980 E 1 000 | K100: PINHEIROS | L100: VINCULACAO | M100: 083177; | N100: 0012-7; 0013-5; | O100: 1861 | P100: R | Q100: 5583 | W100: =T100+Q100 -> 5583 | X100: CEPAC (título) | Z100: 1994 | AA100: 150 | AB100: =AA100+Z100 -> 2144 | AC100: FL-010/2011 | AD100: VALIDA | AE100: 40702 | AK100: GIULIA/27/05/2025
...

Sheet 3_controle_certidoes
A1: TIPO | B1: PROCESSO | C1: DATA DA EMISSAO | D1: PROPOSTA | E1: OUC | F1: NUMERO | G1: ANO_CERTIDAO | H1: NUMERO DA CERTIDAO
C2: XX/XX/XXXX | D2: XX-0000 | E2: XX | F2: 000 | G2: 0 | H2: XX-000/0000 | J2: MODELO
A3: ALTERAÇÃO | B3: 7810.2024/0001277-6 | C3: 45835 | D3: FL-0399 | E3: FL | F3: 001 | G3: 2025 | H3: FL-001/2025
A4: ALTERAÇÃO | B4: 7810.2024/0001318-7 | C4: 45835 | D4: FL-0414 | E4: FL | F4: 002 | G4: 2025 | H4: FL-002/2025
A5: ALTERAÇÃO | B5: 7810.2024/0001498-1 | C5: 45856 | D5: FL-9413 | E5: FL | F5: 003 | G5: 2025 | H5: FL-003/2025
A6: ALTERAÇÃO | B6: 7810.2024/0001324-1 | C6: 45511 | D6: FL-0383 | E6: FL | F6: 004 | G6: 2025 | H6: FL-004/2025
A7: DESVINCULAÇÃO | B7: 7810.2025/0000957-2 | D7: FL-0414 | E7: FL | F7: 001 | G7: 2025 | H7: DV-001/2025
A8: ALTERAÇÃO | B8: 7810.2025/0000957-2 | C8: 45954 | D8: FL-0414 | E8: FL | F8: 005 | G8: 2025 | H8: FL-005/2025
A9: ALTERAÇÃO | B9: 1010.2025/0008826-4 | C9: 45946 | D9: FL-0424 | E9: FL | F9: 006 | G9: 2025 | H9: FL-006/2025
A10: VINCULAÇÃO | B10: 1010.2025/0008932-5 | C10: 45951 | D10: FL-0457 | E10: FL | F10: 007 | G10: 2025 | H10: FL-007/2025
A11: VINCULAÇÃO | B11: 1010.2025/0008862-0 | C11: 45951 | D11: FL-0452 | E11: FL | F11: 008 | G11: 2025 | H11: FL-008/2025
A12: VINCULAÇÃO | B12: 1010.2025/0008856-6 | C12: 45958 | D12: FL-0451 | E12: FL | F12: 009 | G12: 2025 | H12: FL-009/2025
A13: VINCULAÇÃO | B13: 1010.2025/0008833-7 | C13: 45958 | D13: FL-0445 | E13: FL | F13: 010 | G13: 2025 | H13: FL-010/2025
A14: VINCULAÇÃO | B14: 1010.2025/0008838-8 | C14: 45958 | D14: FL-0447 | E14: FL | F14: 011 | G14: 2025 | H14: FL-011/2025
A15: ALTERAÇÃO | B15: 1010.2025/0008851-5 | C15: 45958 | D15: FL-0399 | E15: FL | F15: 012 | G15: 2025 | H15: FL-012/2025
A16: VINCULAÇÃO | B16: 1010.2025/0008831-0 | C16: 45960 | D16: FL-0444 | E16: FL | F16: 013 | G16: 2025 | H16: FL-013/2025
A17: VINCULAÇÃO | B17: 1010.2025/0008877-9 | C17: 45959 | D17: FL-0454 | E17: FL | F17: 014 | G17: 2025 | H17: FL-014/2025
A18: VINCULAÇÃO | B18: 1010.2025/0008829-9 | C18: 45959 | D18: FL-0442 | E18: FL | F18: 015 | G18: 2025 | H18: FL-015/2025
A19: VINCULAÇÃO | B19: 1010.2025/0008837-0 | C19: 45966 | D19: FL-0446 | E19: FL | F19: 016 | G19: 2025 | H19: FL-016/2025
... A29: VINCULAÇÃO | B29: 1010.2025/0008885-0 | C29: 46007 | D29: FL-0456 | E29: FL | F29: 025 | G29: 2025 | H29: FL-025/2025
A30: VINCULAÇÃO | B30: 1010.2025/0008830-2 | D30: FL-0443 | E30: FL | F30: 001 | G30: 2026 | H30: FL-001/2026
A31: DESVINCULAÇÃO | B31: 7810.2025/0001181-0 | D31: FL-0114 | E31: FL | F31: 001 | G31: 2026 | H31: DV-001/2026
A32: DESVINCULAÇÃO | B32: 7810.2025/0001104-6 | C32: 45963 | D32: FL-0383 | E32: DV | F32: 002 | G32: 2025 | H32: DV-002/2025
A33: VINCULAÇÃO | B33: 1010.2025/0008830-2 | C33: 46038 | D33: FL-0443 | E33: FL | F33: 001 | G33: 2026 | H33: FL-001/2026
E35: FL | F35: 002 | G35: 2026 | H35: FL-002/2026 | I35: próxima numeração (inserir linha acima) | J35: VINCULAÇÃO
E36: FL | F36: 002 | G36: 2026 | H36: DV-002/2026 | I36: próxima numeração (inserir linha acima) | J36: DESVINCULAÇÃO

Sheet 4_resumo_propostas
B1: CERTIDAO - 1 | C1: CERTIDAO - 2 | D1: CERTIDAO - 3 | E1: CERTIDAO - 4 | F1: CERTIDAO - 5 | G1: CERTIDAO - 6 | H1: CERTIDAO - 7 | I1: CERTIDAO - 8
A2: FL-0001 | B2: FL-005/1995
A3: FL-0002 | B3: FL-012/1995
A4: FL-0003 | B4: FL-025/1996
A5: FL-0004 | B5: FL-103/1996 | C5: FL-135/1997
A6: FL-0005 | B6: FL-044/1996
A7: FL-0006
A8: FL-0007 | B8: FL-063/1997 | C8: FL-016/2000
A9: FL-0008 | B9: FL-112/1997
A10: FL-0009
A11: FL-0010 | B11: FL-038/1996
A12: FL-0011 | B12: FL-102/1996 | C12: FL-071/1997
A13: FL-0012 | B13: FL-061/1996 | C13: FL-074/1996
A14: FL-0013
A15: FL-0014 | B15: FL-020/1996
A16: FL-0015 | B16: FL-065/1996
A17: FL-0016 | B17: FL-071/1996
A18: FL-0017 | B18: FL-039/1996
A19: FL-0018
A20: FL-0019 | B20: FL-010/1996 | C20: FL-058/1996 | D20: FL-014/1998 | E20: FL-001/2000
A21: FL-0020 | B21: FL-021/1996
A22: FL-0021 | B22: FL-029/1996
A23: FL-0022 | B23: FL-034/1996
A24: FL-0023
A25: FL-0024
A26: FL-0025
A27: FL-0026 | B27: FL-040/1997
A28: FL-0027
A29: FL-0028 | B29: FL-043/1997
A30: FL-0029 | B30: FL-042/2000
A31: FL-0030
A32: FL-0031 | B32: FL-024/1997 | C32: FL-002/2004
A33: FL-0032 | B33: FL-104/1996
A34: FL-0033 | B34: FL-033/1997
A35: FL-0034 | B35: FL-032/1997 | C35: FL-001/1998
A36: FL-0035 | B36: FL-041/1998
A37: FL-0036 | B37: FL-058/1997 | C37: FL-040/1998
A38: FL-0037
A39: FL-0038 | B39: FL-031/1997
A40: FL-0039 | B40: FL-078/1997 | C40: FL-032/1998
A41: FL-0040 | B41: FL-016/1998
A42: FL-0041 | B42: FL-003/2000
A43: FL-0042
A44: FL-0043
A45: FL-0044 | B45: FL-057/1997
A46: FL-0045
A47: FL-0046 | B47: FL-067/1997
A48: FL-0047
A49: FL-0048 | B49: FL-009/1998
A50: FL-0049
A51: FL-0050 | B51: FL-102/1997 | C51: FL-012/1999 | D51: FL-036/2000
A52: FL-0051 | B52: FL-016/1999
A53: FL-0052 | B53: FL-081/1997
A54: FL-0053 | B54: FL-099/1997
A55: FL-0054 | B55: FL-039/1998
A56: FL-0055
A57: FL-0056 | B57: FL-129/1997
A58: FL-0057
A59: FL-0058
A60: FL-0059 | B60: FL-077/1997
A61: FL-0060 | B61: FL-013/1998
A62: FL-0061 | B62: FL-133/1997
A63: FL-0062 | B63: FL-034/1998
A64: FL-0063 | B64: FL-142/1997
A65: FL-0064
A66: FL-0065 | B66: FL-035/1998
A67: FL-0066 | B67: FL-031/2000
A68: FL-0067 | B68: FL-042/1998
A69: FL-0068
A70: FL-0069 | B70: FL-005/1999
A71: FL-0070 | B71: FL-017/1998
A72: FL-0071
A73: FL-0072
A74: FL-0073
A75: FL-0074
A76: FL-0075 | B76: FL-010/1999
A77: FL-0076
A78: FL-0077 | B78: FL-045/1998
A79: FL-0078 | B79: FL-018/1999
A80: FL-0079 | B80: FL-002/1999
A81: FL-0080 | B81: FL-023/1999
A82: FL-0081
A83: FL-0082 | B83: FL-043/1998
A84: FL-0083 | B84: FL-044/1998
A85: FL-0084 | B85: FL-008/1999
A86: FL-0085 | B86: FL-001/1999
A87: FL-0086 | B87: FL-003/1999
A88: FL-0087
A89: FL-0088
A90: FL-0089 | B90: FL-027/1999 | C90: FL-014/2000
A91: FL-0090 | B91: FL-005/2000
A92: FL-0091 | B92: FL-006/1999
A93: FL-0092 | B93: FL-017/1999
A94: FL-0093
A95: FL-0094 | B95: FL-015/1999
A96: FL-0095 | B96: FL-001/2014
A97: FL-0096
A98: FL-0097 | B98: FL-022/1999
A99: FL-0098 | B99: FL-007/2000
A100: FL-0099 | B100: FL-021/1999
...

Sheet METADADOS
A2: Variáveis | B2: Descrição da Variável | C2: Exemplo:
A3: CODIGO | B3: Número da PROPOSTA de vinculação de CEPACs. Campo alfa numérico. Iniciar o número 9 quando houver remembramento de proposta. Iniciar com a letra X quando houver duplicidade de códigos de proposta (em casos de equivocos, para identificar que são propostas diferentes. Letra X incluída na Proposta mais recente). | C3: XX-0000 ou XX-9000 ou XX-X000
A4: LEI | B4: Lei válida na emissão da certidão | C4: 13.769/2004, 18.175/2024 | D4: FAZER LISTA SUSPENSA DAS LEIS
A5: PA | B5: Número do processo administrativo gerado quando do protocolo da solicitação inicial do interessado. | C5: 0000.0000/0000000-0 ou 0000-0.000.000-0 | D5: novo padrão
A6: DATA AUTUACAO PA | B6: Data de abertura, email do Interessado | C6: xx/xx/xxxx | D6: novo padrão
A7: STATUS PA | B7: Situação atual do processo administrativo | C7: DEFERIDO, INDEFERIDO, ANALISE | D7: FIXO
A8: INTERESSADO | B8: Nome do Interessado. Escrever sem acento. TUDO MAIUSCULO | C8: XXXXXXXXXXXXXXXXX
A9: CNPJ | B9: Número do CNPJ do interessado | C9: xx.xxx.xxx/xxxx-xx | D9: Novo padrão
A10: ENDEREÇO | B10: Colocar nome da rua e número se houver, escrever nome COMPLETO | C10: xxxxxxxxxxxxxxxxx, 000
A11: SETOR OUC | B11: XXX | C11: CHUCRI ZAIDAN, BERRINI, BROOKLIN, JABAQUARA, MARGINAL PINHEIROS | D11: FAZER LISTA SUSPENSA DO SETOR POR OUC
A12: REQUERIMENTO | B12: Tipo da solicitação realizada | C12: VINCULACAO, ALTERACAO, DESVINCULACAO | D12: FAZER LISTA SUSPENSA DO SETOR POR OUC
A13: CONTRIBUINTE - SQ | B13: setor e lote dos imóveis (seja um sejam vários) separador ";" | C13: XXXXXX; OU XXXXXX;XXXXXX; | D13: ALTERADO - RODGER
A14: CONTRIBUINTE - L | B14: lote dos imóveis (seja um sejam vários) separador ";" | C14: xxxx-x; xxxx-x; xxxx-x; xxxx-x
A15: ÁREA DO TERRENO | B15: Quantidade de m² que o terreno possui (seja um SQL, seja união de vários) utilizar sempre o menor número (real ou escritura) | C15: x.xxx,xx | D15: QUANDO EXISTIR MAIS DE 2 CASAS DEPOIS DA VÍRGULA, ATÉ O NÚMERO 5 ARREDONDAMENTO PARA BAIXO IGUAL OU MAIOR QUE 5 ARREDONDAMENTO PARA CIMA
A16: USO DA ACA | B16: Categoria de uso definida para ACA do empreendimento | C16: R, NR, MISTO | D16: FAZER LISTA SUSPENSA DO SETOR POR OUC
A17: ACA-R | B17: área de construção adicional de uso residencial | C17: x.xxx,xx
A18: ACA-NR | B18: área de construção adicional de uso não residencial | C18: x.xxx,xx
A19: ACA-TOTAL | B19: área de construção adicional total do empreendimento | C19: x.xxx,xx
A20: TIPO DE CONTRAPARTIDA | B20: Tipo de pagamento da outorga onerosa | C20: OODC (dinheiro) CEPAC (título) | D20: FAZER LISTA SUSPENSA DO SETOR POR OUC
A21: VALOR R$ | B21: Pagamento realizado em dinheiro | C21: xx.xxx.xxx,xx | D21: COLUNA SUPRIMIDA
A22: CEPAC ACA | B22: Quatidade de títulos vinculados para ACA | C22: X.XXX
A23: CEPAC PARAMETROS | B23: Quatidade de títulos vinculados para parâmetro urbanísticos | C23: X.XXX
A24: TOTAL CEPAC | B24: Quantidade total de CEPAC vinculada | C24: X.XXX
A25: CERTIDAO | B25: Código da certidão emitida | C25: AB-xxx/2024, AE-xxx/2024, FL-xxx/2024
A26: SITUACAO | B26: Situação da certidão | C26: VALIDA (quando for a ultima certidão emitida) CANCELADA (certidão anterior) | D26: FAZER LISTA SUSPENSA DO SETOR POR OUC
A27: DATA CERTIDAO | B27: Data de emissão da certidão | C27: xx/xx/xxxx
A28: NUVEM m² - R | B28: área de construção adicional de uso residencial na NUVEM | C28: x.xxx,xx
A29: NUVEM m² - nR | B29: área de construção adicional de uso não residencial na NUVEM | C29: x.xxx,xx
A30: NUVEM m² | B30: campo preenchido com de o quantidade de m² constante nas observações na certidão | C30: x.xxx,xx
A31: NUVEM CEPAC - R
A32: NUVEM CEPAC - nR
A33: NUVEM CEPAC | B33: campo preenchido com o quantidade de CEPAC constante nas observações na certidão | C33: XX
A34: OBS | B34: Campo livre para informações complementares. CANCELADA PELA CERTIDÃO XXX | C34: sem padrão
A35: RESP/DATA | B35: Nome de quem realizou o cadastro e data do cadastro | C35: nome/00/00/2024
B36: RETORNO ESTOQUE E CEPAC (DESVINCULAÇÃO) | C36: A DATA QUE VOLTA O CEPAC E O ESTOQUE É SEMPRE A DATA DE PUBLICAÇÃO DO DESPACHO DEFERIDO!

Sheet lista_suspensa
B2: STATUS PA | C2: SETORES | D2: STATUS CERTIDAO | E2: LEI | F2: REQUERIMENTO
B3: DEFERIDO | C3: PINHEIROS | D3: VALIDA | E3: 13.769/2004 | F3: VINCULACAO
B4: ANALISE | C4: FARIA LIMA | D4: CANCELADA | E4: 18.175/2024 | F4: DESVINCULACAO
B5: INDEFERIDO | C5: HÉLIO PELEGRINO | F5: ALTERACAO
C6: OLIMPÍADAS
